Workbook

Sheet (과제 승인 후)2.실행과제LIST

Sheet 1.아이디어LIST
A1: ○ 아이디어LIST | AB1: 변경전 | AD1: 구 분 | AE1: 본 사 | AF1: 현 장 | AG1: 전체 | AJ1: 변경후 | AK1: 구분 | AL1: 건축 | AM1: 개발 | AN1: 인프라 | AO1: 지원 | AP1: 전체 | AR1: 건축 | AS1: 개발 | AT1: 인프라 | AU1: 지원 | AV1: 전체
AK2: 보정 | AL2: 4 | AN2: 2 | AO2: 7 | AP2: 13 | AR2: 보정 사유 : 아이디어 제안서 접수 없이 중점과제 진행
AD3: 접수 | AE3: 620 | AF3: 1072 | AG3: 1692 | AK3: 접수 | AL3: 1175 | AM3: 160 | AN3: 194 | AO3: 175 | AP3: 1704 | AR3: FALSE | AS3: FALSE | AT3: T | AU3: FALSE | AV3: FALSE
A4: - 문서 목적: 1. 아이디어 내용 정리(보고 자료 및 데이터 사용 필요), 2. 아이디어 제안, 채택 포상 지급, 3. 불인정, 불채택 건에 대한 피드백, 4. 업무 그레이존 방지(담당자 명확화, 접수 후 진행상황 점검) | AD4: (불인정) | AE4: 111 | AF4: 315 | AG4: 426 | AK4: (불인정) | AL4: 325 | AM4: 32 | AN4: 39 | AO4: 30 | AP4: 426
AD5: 인정 검토 중 | AE5: 0 | AF5: 0 | AG5: 0 | AK5: 인정 검토중 | AL5: 0 | AM5: 0 | AN5: 0 | AO5: 0 | AP5: 0
D6: 아이디어 접수자, 작성 | H6: 검토 후 담당자, 작성 | AD6: 인정 | AE6: 503 | AF6: 754 | AG6: 1257 | AK6: 인정 | AL6: 843 | AM6: 127 | AN6: 155 | AO6: 144 | AP6: 1269 | AR6: T | AS6: T | AT6: T | AU6: T | AV6: T
AD7: (불상정) | AE7: 375 | AF7: 696 | AG7: 1071 | AK7: (불상정) | AL7: 727 | AM7: 116 | AN7: 130 | AO7: 98 | AP7: 1071
A8: NO | B8: Code | C8: 제안자 | I8: 제안일 | J8: TOP추진실 담당자 | K8: 담당자 | L8: 아이디어 제안 요약 | Q8: 검토 | V8: 주요 일정 관리 | X8: 포상 시기 | AA8: 비고 | AB8: 0 | AD8: 상정 검토 중 | AE8: 33 | AF8: 24 | AG8: 57 | AK8: 상정 검토 중 | AL8: =COUNTIFS($Q:$Q,"검토중",$C:$C,"건축") -> 8 | AM8: =COUNTIFS($Q:$Q,"검토중",$C:$C,"개발") -> 0 | AN8: =COUNTIFS($Q:$Q,"검토중",$C:$C,"인프라") -> 3 | AO8: {=+SUM(COUNTIFS($Q:$Q,"검토중",$C:$C,{"인사지원","기획실","기획","안전환경","직속부서","직속","법무실"}))} -> 2 | AP8: =SUM(AL8:AO8) -> 13
C9: 본부 | D9: 사업장 | E9: 사번 | F9: 직급 | G9: 소속 | H9: 성명 | I9: 제안일 | J9: (참고) 검토담당 | K9: 1차 검토 담당자 | L9: 대분류 | M9: 중분류 | N9: 소분류 | O9: 제안 제목 | P9: 제안 내용 상세 | Q9: 제안 인정 | R9: 채택 현황 | S9: 인정 점수 | T9: 채택 점수 | U9: 검토 의견 및 제안자 피드백 | V9: CFT구성 여부 | W9: 과제승인위원회 상정 여부 | X9: 제안 인정 | Y9: 채택 포상 | Z9: 피드백 완료 여부 | AB9: 중복 | AD9: 승인위(예정) | AE9: 80 | AF9: 25 | AG9: 105 | AK9: 승인위(예정) | AL9: =+COUNTIFS($R:$R,"o",$C:$C,"건축")+4 -> 84 | AM9: =+COUNTIFS($R:$R,"o",$C:$C,"개발") -> 4 | AN9: =+COUNTIFS($R:$R,"o",$C:$C,"인프라")+2 -> 12 | AO9: {=SUM(COUNTIFS($R:$R,"O",$C:$C,{"인사지원","기획실","기획","안전환경","외주구매","직속부서","직속","법무실"}))+7} -> 36 | AP9: =SUM(AL9:AO9) -> 136
AD10: 실행 | AE10: 0 | AF10: 0 | AG10: 0 | AK10: 실행 | AL10: 59 | AM10: 2 | AN10: 5 | AO10: 28 | AP10: 94
A11: 1 | B11: PR/P-M-CE-1 | C11: 건축 | D11: 현장 | E11: 2102486 | F11: 대리 | G11: 춘천 프리미엄 빌리지 건설공사 | H11: 황준하 | I11: 45474 | J11: 박재보, 박병규, | K11: 박재보 | L11: 구매 | M11: 기계 | N11: 공사비 | O11: (지급자재 전환) 욕실휀 지급자재 전환 및 연간단가 체결 | P11: • 욕실휀 연간단가로 지정하여 지급자재로 전환 시 재료비 절감 효과 기대. 공동주택 세대 수가 많을수록 절감효과가 클 것으로 예상(ex 온도조절기) | Q11: O | R11: O | S11: 28 | T11: 82 | V11: O | W11: 3차(240909) | X11: 24년3분기(240920) | Y11: 24년3분기(240920) | Z11: Case4. (채택)피드백 완료 | AD11: 목요일 오전 8시 기준 주간 업무일정 작성예정 | AL11: 건축 | AM11: 개발 | AN11: 인프라 | AO11: 지원 | AP11: 합계
A12: 2 | B12: CO/Z-ID/A-CE-1 | C12: 건축 | D12: 본사 | E12: 2000173 | F12: 대리 | G12: TOP추진실 | H12: 최재형 | I12: 45474 | J12: 차원재, 양창모, 차원재 | K12: 박재보 | M12: 보험료 | N12: 공사비 | O12: 산재보험료 산출 정확도 향상을 통한 원가추정 ↑ | P12: • (유형효과) 절감 예상 금액 = 납품성 공종 금액x30%(노무비율) x2.66% (추정 집행 요율) • (투자비) 원가코드 개선을 위한 프로그래밍비용 • (과제수행 기간) 24년 08월 ~25년 07월(12달) • (기타) 납품성 자재비(MEP장비납품 등)의 금액이 큰 현장의 경우 해당금액이 산재보험료 집행 모수에 반영되어 산재보험료 금액 상승 | Q12: O | R12: X | S12: 20 | T12: 68 | U12: 손익에 영향이 없는 내용. 다만, 회사의 투입(IT시스템 개발+매월 관리 인력) 대비 내부 원가관리의 원활/정확성을 위해 추진할 것인가에 대해서는 논의하였으나 현재는 필요성이 낮고 담당자가 매월 모든 계약 건을 확인하여야 되서 현실적으로 업무가 더 늘어남. 매월 고용산재 전사 금액(3월 년납 선급처리 후 1/12을 매월 원가 처리)을 본사/각 현장의 (직접인건비+간접인건비(외주/자재비*노무비율30%))*고용산재요율)를 기준으로 분배되어 본사/각 현장으로 원가투입이 됨. 특정현장이 실재 고용산재 납부시, 포함되지 않은 항목이 원가 배분시 투입되면 그 현장의 원가가 늘어나지만 타 현장의 원가는 줄어듬. 전사로 보면 동일함. | X12: 24년3분기(240920) | Z12: Case2. (인정O,채택X)피드백 완료 | AL12: 13
A13: 3 | B13: CO/I-TF-CE-1 | C13: 건축 | D13: 본사 | E13: 1907086 | F13: 대리 | G13: 건축견적팀 | H13: 조윤재 | I13: 45474 | J13: 양창모, 박준용, 양창모 | K13: 양창모 | L13: 수행-비공사성 | M13: 공통가설 | N13: 공사비 | O13: 폐기물 처리비 투입기준 최신화, 혼폐 체적당 계약 및 집게차 운영을 통한 부피축소 | P13: • (유형효과) 24년 실행대비 5% 절감, 25년 실행대비 6% 절감 • (투자비) 1,500만원(=집게차 임대료 250만원x6개월) [VAT 제외] • (과제수행 기간) 24년 08월 ~25년 08월(12달) • (기타) 실행편성 기준 현실화(혼폐, m3당 단가 적용), 현장 분리수거 강화 노력 | Q13: O | R13: O | S13: 25 | T13: 71 | V13: O | W13: 7차(250114) | X13: 24년3분기(240920) | Y13: 25년1분기(000000) | Z13: Case3. (인정O,채택 검토)피드백 완료 | AL13: 62 | AO13: 45
A14: 4 | B14: EN/EX-A/F-CE-1 | C14: 건축 | D14: 본사 | E14: 1103501 | F14: 차장 | G14: 건축견적팀 | H14: 정관희 | I14: 45474 | J14: 김태용, 송원일, 김태용 | K14: 김태용 | L14: 설계_건축외부 | M14: 건축_마감 | N14: 공사비 | O14: 공동주택 외벽마감재 석재 → 세라믹타일 | P14: • 석재 대체 자재 발굴 및 적용 - 상품성을 저해하지 않으면서 석재의 역할을 대신할 수 있는 자재 발굴 및 적용 - 기술혁신파트너몰 (https://partner.lh.or.kr/promote/view.asp)에 등재된 외장타일 적용 여부 검토 필요 - 경량(10T) 자재이며 등재된 단가 25,000원/M2로 시공성과 원가 절감 가능 - 인건비 절감 효과 클 것으로 기대 (협력사 인터뷰 및 견적수취로 추후 효과검증) - 시공사례 적어 현장 견학 필요 (춘천 파밀리에 리버파크_신동아건설) | Q14: O | R14: X | S14: 18 | T14: 58 | U14: (1차검토 : 미채택) 포레나2.0은 단일석종 100%적용 중이며 해당석종(오련회) 자재단가는 20,000원 초중반/M2 수준으로 제안자재의 유의미한 절감 효과 없음 | X14: 24년3분기(240920) | Z14: Case2. (인정O,채택X)피드백 완료 | AL14: 1106 | AO14: 181
A15: 5 | B15: EN/I-A/F-CE-1 | C15: 건축 | D15: 본사 | E15: 2202075 | F15: 과장 | G15: 건축견적팀 | H15: 임정근 | I15: 45474 | J15: 김태용, 송원일, 김태용 | K15: 김태용 | L15: 설계_건축내부 | M15: 건축_마감 | N15: 공사비 | O15: 욕실 골조벽면 액체방수 삭제 | P15: 욕실 벽체중 콘크리트면의 액체방수 설계제외 (단, 조적벽과 만나는 코너부위 도막방수보강등은 유지) | Q15: O | R15: X | S15: 21 | T15: 67 | U15: (1차검토 : 미채택) '23년 외주 SE 2기 기 시행사항 | X15: 24년3분기(240920) | Z15: Case2. (인정O,채택X)피드백 완료 | AK15: 아이디어 제안 | AL15: =COUNTIFS($C:$C,"건축") -> 1310 | AM15: =COUNTIFS($C:$C,"개발") -> 164 | AN15: =COUNTIFS($C:$C,"인프라") -> 250 | AO15: =1850-SUM(AL15:AN15) -> 126
A16: 6 | B16: EN/I-A/F-CE-2 | C16: 건축 | D16: 본사 | E16: 2200403 | F16: 대리 | G16: 건축견적팀 | H16: 이현지 | I16: 45474 | J16: 김태용, 송원일, 김태용 | K16: 김태용 | L16: 설계_건축내부 | M16: 건축_마감 | N16: 공사비 | O16: 현관 타일 사이즈 변경 600*600 → 300*300 | P16: • 현관창고는 수납의 공간으로 당사의 경우 현관과 동일한 타일 적용 | Q16: O | R16: X | S16: 24 | T16: 통합 (186번) | U16: (1차검토 : 타 과제와 통합) | X16: 24년3분기(240920) | Z16: Case2. (인정O,채택X)피드백 완료 | AA16: 통합 (186번) | AK16: 과제화 진행 | AL16: 82 | AM16: 4 | AN16: 12 | AO16: 36
A17: 7 | B17: PR/P-M-CE-2 | C17: 건축 | D17: 본사 | E17: 2201216 | F17: 대리 | G17: 건축견적팀 | H17: 이현준 | I17: 45474 | J17: 박재보, 박병규, | K17: 박재보 | L17: 구매 | M17: 기계 | N17: 공사비 | O17: (지급자재 전환) 외주계약 휀류(Ex. 지하 유인휀) → 구매자재 변경 | P17: - 현재 유인휀은 기계설비공사(외주공사) 내 자재비+노무비로 편성되어 있음 - 기계설비업체 입찰 단가에 의해 유인휀 단가 편차가 생김 | Q17: O | R17: O | S17: 26 | T17: 82 | V17: O | W17: 3차(240909) | X17: 24년3분기(240920) | Y17: 24년3분기(240920) | Z17: Case4. (채택)피드백 완료 | AF17: 지난주 | AG17: 1114 | AH17: 144 | AI17: 162 | AJ17: 168 | AK17: 1588 | AL17: <<여기부터 갱신
A18: 8 | B18: EN/E-E-CE-1 | C18: 건축 | D18: 본사 | E18: 1700070 | F18: 대리 | G18: 건축견적팀 | H18: 이상준 | I18: 45474 | J18: 오정화, 오정화, | K18: 오정화 | L18: 설계_전기 | M18: 전기 | N18: 공사비 | O18: 강제전선관 타입변경 (후강전선관→나사없는 전선관) | P18: • 나사없는전선관 사용시 나사산이 없는 방식의 연결로 배관을 보다 쉽고 빠르게 체결 가능 (볼트식 이음쇠 및 부속품 사용) • 후강전선관 대비 경량으로 취급이 용이하여 시공성 향상에 의한 노무비 절감 가능 | Q18: O | R18: O | S18: 25 | T18: 87 | V18: O | W18: 3차(240909) | X18: 24년3분기(240920) | Y18: 24년3분기(240920) | Z18: Case4. (채택)피드백 완료 | AF18: 금주 | AG18: 1175 | AH18: 160 | AI18: 194 | AJ18: 175 | AK18: 1704
A19: 9 | B19: CO/I-TF-CE-2 | C19: 건축 | D19: 현장 | E19: 0703047 | F19: 차장 | G19: 창원IDC 신축공사 | H19: 윤재만 | I19: 45474 | J19: 양창모, 박준용, 양창모 | K19: 박병규 | L19: 수행-비공사성 | M19: 공통가설 | N19: 공사비 | O19: 간이소화장치 재사용 (준공현장 자재 타현장 재사용) | P19: • 기존 현장의 준공 이전 가설 해체 시점에 간이소화장치 이동식 및 고정식을 신규 현장으로 이관하여 재설치 활용이 가능하고, 해당 현장 실행 편성 시 적용 여부에 따른 실행 감액 편성을 통한 원가 절감 가능 | Q19: O | R19: X | S19: 20 | T19: 68 | U19: 재사용 아이디어는 좋으나, 과거 유사한 형태로 진행되었던 사례를 봤을때, 현장에서 기존제품 관리 및 재사용화(제품화)가 어려워 전문업체를 통한 리사이클이 효과적이라 생각됨 | X19: 24년3분기(240920) | Z19: Case2. (인정O,채택X)피드백 완료 | AF19: 신규접수 | AG19: 61 | AH19: 16 | AI19: 32 | AJ19: 7 | AK19: 116
A20: 10 | B20: EN/E-E-CE-2 | C20: 건축 | D20: 본사 | E20: 0700716 | F20: 차장 | G20: 건축견적팀 | H20: 송인홍 | I20: 45474 | J20: 오정화, 오정화, | K20: 오정화 | L20: 설계_전기 | M20: 전기 | N20: 공사비 | O20: 무인택배시설 삭제 | P20: • 무인택배설비의 사용성 저하로 인해 FORENA 기본설계에서 삭제를 검토하고 별도로 건축심의 또는 조합(발주처)의 요구, LH/SH 심의의견 등에 따라서 선별 적용하는 기준으로 변경하는 것을 검토하고자 함 | Q20: O | R20: X | S20: 21 | T20: 63 | U20: 일괄 삭제 또는 최적화(수량 최소화)와 관련하여 사업팀 협의가 필요한 제안임. 추후 재검토 예정 | X20: 24년3분기(240920) | Z20: Case2. (인정O,채택X)피드백 완료 | AG20: 건축 | AH20: 개발 | AI20: 인프라 | AJ20: 지원 | AK20: 합계
A21: 11 | B21: EN/M-M-CE-1 | C21: 건축 | D21: 본사 | E21: 2203377 | F21: 과장 | G21: 건축견적팀 | H21: 송성무 | I21: 45474 | J21: 박병규, 박병규, | K21: 박병규 | L21: 설계_기계 | M21: 기계 | N21: 공사비 | O21: 공동주택 세대 수도계량기함 동파방지열선 변경 | P21: • [공동주택 개선방안] : 세대 계량기 양수기함內 동파방지용 전기열선 일부층 보온솜으로 변경 - 지상1~2층, 최상층 : 양수기함(스티로폼) + 동파방지용 전기열선(1M) - 지상3층 ~ 최상층의 직하층 : 양수기함(스티로폼) + 보온솜  동파 우려가 적은 층(지상3층~최상층의 직하층) 열선 삭제, 보온솜으로 대체 | Q21: O | R21: O | S21: 19 | T21: 80 | U21: 타사 사례 및 건축기계팀과 검토하여 15차 승인위원회 과제화 예정 | V21: O | W21: 15차(251104) | X21: 24년3분기(240920) | Y21: 25년3,4분기(251209) | Z21: Case2. (인정O,채택X)피드백 완료
A22: 12 | B22: CO/I-TF-CE-3 | C22: 건축 | D22: 해외 | E22: 0600067 | F22: 차장 | G22: 건축지원팀(파견) | H22: 성정각 | I22: 45474 | J22: 양창모, 박준용, 양창모 | K22: 박병규 | L22: 수행-비공사성 | M22: 공통가설 | N22: 공사비 | O22: 준공현장 소화기 타현장 이관 | P22: • 프로세스를 정립하여 준공현장의 소화기를 필요한 현장으로 이관 각현장 별 소방안전관리자 취합 -> 현장 관리팀 건축지원팀 보고후 이관 -> 이관현장은 이관물량 제외 발주 | Q22: O | R22: X | S22: 20 | T22: 68 | U22: 재사용 아이디어는 좋으나, 과거 유사한 형태로 진행되었던 사례를 봤을때, 현장에서 기존제품 관리 및 재사용화(제품화)가 어려워 전문업체를 통한 리사이클이 효과적이라 생각됨 | X22: 24년3분기(240920) | Z22: Case2. (인정O,채택X)피드백 완료
A23: 13 | B23: CO/D-A/F-CE-1 | C23: 건축 | D23: 본사 | E23: 2203417 | F23: 과장 | G23: 건축견적팀 | H23: 박민석 | I23: 45474 | J23: 안희진, 송원일, 김태용 | K23: 안희진 | L23: 수행-공사성 | M23: 건축_마감 | N23: 공사비 | O23: 현관문 보양지 준공청소 제거 → 입주자 직접제거로 변환 | P23: • 상위 타 건설사는 근래 방화문 보양지를 입주 후 입주자가 제거하게 하여 원인미상 하자를 미연에 방지. (타공종 긁힘 하자 등) • 세대현관문 설치 후 디지털도어락 설치 전까지 간이 도어핸들 또는 도어체크를 즉시 설치하여 바람 등의 의한 충격 파손 하자를 방지하여 AS원가 절감. | Q23: X | S23: 14 | U23: 현재에도 입주자 직접 제거분으로 처리하는 현장이 있습니다. 공사팀 관계자의 의사결정을 통해 결정할 수 있는 사항이어서 아이디어로 채택되지 않았습니다. | Z23: Case1. (인정X)피드백 완료
A24: 14 | B24: EN/S-C-CE-1 | C24: 건축 | D24: 본사 | E24: 1500183 | F24: 과장 | G24: 건축견적팀 | H24: 김태경 | I24: 45474 | J24: 박준용, 박준용, 양창모 | K24: 박준용 | L24: 구조/토목 | M24: 토목 | N24: 공사비 | O24: 흙막이 ↔ 외벽간 너비를 감안한 설계로 투입비용 절감 | P24: • 합벽-흙막이 간격 축소 방안 검토(Case별 축소 방안마련) • 각종 심의 후 흙막이 Line 변경은 어려우므로 심의전 설계검토하여 흙막이 Line 최적화 실시 | Q24: O | R24: X | S24: 18 | T24: 69 | U24: 아이디어 인정, 과제 미채택 유관부서(기술혁신팀, 건축견적팀) 협의 통하여 비합벽 이격치수 확정 및 공유에 대한 필요성이 있습니다. | X24: 24년3분기(240920) | Z24: Case2. (인정O,채택X)피드백 완료
A25: 15 | B25: EN/I-A/F-CE-3 | C25: 건축 | D25: 본사 | E25: 1500183 | F25: 과장 | G25: 건축견적팀 | H25: 김태경 | I25: 45474 | J25: 김태용, 송원일, 김태용 | K25: 김태용 | L25: 설계_건축내부 | M25: 건축_마감 | N25: 공사비 | O25: 상가 바닥마감 기준 변경 비닐계타일 → 무근 | P25: • 상가 바닥 마감변경(무근+비닐계타일 → 무근 마감) - 분양시, 상가바닥 마감은 무근 마감임을 사전에 공지 • 상가 벽, 천정 마감도 사전에 마감 진행여부 확인 및 서명을 받아 삭제가 가능하다면 삭제 - 벽, 천정마감도 개별인테리어 실시로 마감을 원치 않은 계약자 발생 • 기타시설(지식산업센터, 업무시설) 등에도 점차 확대 적용 | Q25: X | S25: 14 | U25: (1차검토 : 미채택) 순수 분양형 근생 및 판매시설에 적용할 가능성이 있는 제한적 아이디어로, 발주처(시행사, 조합 등)와 협의 진행 시 마감 제외 외 별도 추가 요청이 빈번하여 오히려 현장 실행에 부담 줄 가능성이 높음 | Z25: Case1. (인정X)피드백 완료
A26: 16 | B26: CO/I-TF-CE-4 | C26: 건축 | D26: 본사 | E26: 1803688 | F26: 대리 | G26: 건축견적팀 | H26: 김주상 | I26: 45474 | J26: 양창모, 박준용, 양창모 | K26: 양창모 | L26: 수행-비공사성 | M26: 공통가설 | N26: 공사비 | O26: 승강기 설치전 E.V홀 또는 외부 윈치 설치하여 양중 및 하역 | P26: • 엘리베이터 설치 전 엘리베이터 통로 또는 발코니 외부에 윈치를 설치하여 양중 및 하역 진행 | Q26: O | R26: X | S26: 22 | T26: 50 | U26: 아이디어가 참신하여 아이디어 제안 인정되나, 안전에 대한 심층적 검토가 필요하여 미채택 | X26: 24년3분기(240920) | Z26: Case2. (인정O,채택X)피드백 완료
A27: 17 | B27: EN/EX-A/F-CE-2 | C27: 건축 | D27: 본사 | E27: 1000198 | F27: 차장 | G27: 건축견적팀 | H27: 구민정 | I27: 45474 | J27: 김태용, 송원일, 김태용 | K27: 김태용 | L27: 설계_건축외부 | M27: 건축_마감 | N27: 공사비 | O27: 공동주택 저층부 석재마감 최소화 | P27: • 지상1층(입주민의 접촉 구간)은 석재50%수준으로 적용하고, 지상2~3층 및 단차부(옹벽 등) 주1을 및 근생부 외벽은 석재뿜칠 적용하여 원가 경쟁력 확보 • 분양성 저해의 소지는 있으나, 심의 전 변경이 가능한 경우 적용 확대 • 조경 특화의 사례처럼 포레나 외부 특화 아이템을 별도로 만들어 준공시점 설계변경으로 도급 증액 유도 | Q27: O | R27: X | S27: 19 | T27: 65 | U27: (1차검토 : 미채택) 포레나2.0은 단일석종 100%적용 중이며 해당석종(오련회) 자재단가는 20,000원 초중반/M2 수준으로 제안자재의 유의미한 절감 효과 없음 | X27: 24년3분기(240920) | Z27: Case2. (인정O,채택X)피드백 완료
A28: 18 | B28: EN/I-A/S-CE-1 | C28: 건축 | D28: 본사 | E28: 1000198 | F28: 차장 | G28: 건축견적팀 | H28: 구민정 | I28: 45474 | J28: 김태용, 송원일, 박준용 | K28: 김태용 | L28: 설계_건축내부 | M28: 건축_골조 | N28: 공사비 | O28: PIT 최소화를 통한 원가율 개선 | P28: • 충주 용산 현장의 사례처럼 세대창고로 활용하거나, 포레나 지하 특화아이템을 개발 • 마감 공사가 단순한 수준 - 단위 세대별 지하 창고 - 악기 연주 (드럼, 색소폰 등) 소음이 커서 집에서 하기 어려운 취미 활동 공간 | Q28: O | R28: X | S28: 18 | T28: 64 | U28: (1차검토 : 미채택) 지하 PIT 적용할 공간 아이템이 직접 제시되지 못 함 | X28: 24년3분기(240920) | Z28: Case2. (인정O,채택X)피드백 완료
A29: 19 | B29: EN/I-A/F-CE-4 | C29: 건축 | D29: 본사 | E29: 1000198 | F29: 차장 | G29: 건축견적팀 | H29: 구민정 | I29: 45474 | J29: 김태용, 송원일, 김태용 | K29: 김태용 | L29: 설계_건축내부 | M29: 건축_마감 | N29: 공사비 | O29: 대림 이앤씨 평면 벤치마킹 및 무상제공 품목 조정 | P29: • 대림이앤씨 평면 적용으로 절감 가능한 사항 (84이상 타입 기준) - 확장시 안방 발코니 삭제 등 평면 조정 1. 안방부위: 분합창, 대피구간 SD 1개소, 조적벽량 삭제 2. 알파룸 WD 1개 및 주방팬트리도어 1개 삭제 - 무상제공 삭제 1. 팬트리 시스템선반 (ㄷ → ㅡ) 변경 2. 욕실 하1갑 옵션 판매 (당사 카운터탑 무상제공), 발코니 세탁선반 삭제 (당사 무상제공) • 검토 제외 사항 1. 골조 벽량 (향후, 기술팀/기계/전기팀과 협업 필요) | Q29: O | R29: X | S29: 24 | T29: 통합 (중점) | U29: (1차검토 : 중점과제와 통합) 타사 평면들을 참조하여 절감형 포레나 평면 개발이 중점과제로 진행되고 있습니다. 아이디어로 인정되나 과제진행은 중점과제로 병합되어 진행될 예정입니다. | X29: 24년3분기(240920) | Z29: Case2. (인정O,채택X)피드백 완료
A30: 20 | B30: EN/E-E-CE-3 | C30: 건축 | D30: 본사 | E30: 2202060 | F30: 대리 | G30: 건축견적팀 | H30: 강대구 | I30: 45474 | J30: 오정화, 오정화, | K30: 오정화 | L30: 설계_전기 | M30: 전기 | N30: 공사비 | O30: EPS실 콘센트 삭제 | P30: • 아파트 EPS실 각종 전원 콘센트로 유지관리 콘센트 겸용 가능 • 타사 GS건설 EPS실 유지관리 콘센트 미설계 | Q30: O | R30: X | S30: 18 | T30: 62 | U30: 마감공사작업시 공사용 전원으로 유용하다는 현장의견이 많음. 공동주택의 경우 대부분 EPS/TPS 겸용으로 통신장비 예비 전원용으로도 활용가능 (ISP, 이동통신 등) | X30: 24년3분기(240920) | Z30: Case2. (인정O,채택X)피드백 완료
A31: 21 | B31: EN/S-A/S-CE-1 | C31: 외주구매 | D31: 본사 | E31: 1907089 | F31: 대리 | G31: 구매팀 | H31: 권효준 | I31: 45474 | J31: 박준용, 송원일, 박준용 | K31: 박준용 | L31: 구조/토목 | M31: 건축_골조 | N31: 공사비 | O31: D22 이하 기둥 철근 이음 시 B급이음 → A급이음 적용 | P31: • D22 이하 기둥 철근 이음 시 A급이음 적용 | Q31: O | R31: X | S31: 18 | U31: 아이디어 인정, 과제 미채택(통합) 해당내용(A급이음 -> 압축이음)을 적용하기 위해서는 원구조설계사의 별도 검토가 필요함(용역비 발생할 수 있음), 기술혁신팀 과제화중이며 현장 누락없이 적용가능한 프로세스를 마련중입니다. | X31: 24년3분기(240920) | Z31: Case2. (인정O,채택X)피드백 완료 | AA31: 통합 (40번)
A32: 22 | B32: CO/Z-PI-EXP-1 | C32: 건축 | D32: 본사 | E32: 0700706 | F32: 차장 | G32: 건축지원팀 | H32: 김필중 | I32: 45474 | J32: 차원재, 박재보, 고한울 | K32: 박재보 | L32: 공통 | M32: 프로세스 개선 | N32: 전사경비 | O32: 벽걸이 달력 미지급 | P32: • 대달력 전 직원 미제공 또는 최소 필요 수량 제공 또는 현장(팀)별 50% 제공 - 효과 발생시 계열사 확대 시행 | Q32: O | R32: X | S32: 20 | T32: 통합 (180번) | X32: 24년3분기(240920) | Z32: Case2. (인정O,채택X)피드백 완료
A33: 23 | B33: CO/I-TF-CE-5 | C33: 건축 | D33: 본사 | E33: 0700706 | F33: 차장 | G33: 건축지원팀 | H33: 김필중 | I33: 45474 | J33: 양창모, 박준용, 양창모 | K33: 오정화 | L33: 수행-비공사성 | M33: 공통가설 | N33: 공사비 | O33: 협력사 가설전기 사용료 부담 | P33: • 협력사 계량기 설치 및 가설전기 사용료 개별 부담에 따른 전력 감소 및 전기사용료 절감 | Q33: O | R33: X | S33: 24 | T33: 통합 (266번) | U33: 266번 제안과 통합 | X33: 24년3분기(240920) | Z33: Case2. (인정O,채택X)피드백 완료
A34: 24 | B34: CO/Z-PI-CE-1 | C34: 건축 | D34: 본사 | E34: 1104096 | F34: 과장 | G34: 건축지원팀 | H34: 문성호 | I34: 45474 | J34: 차원재, 박재보, 고한울 | K34: 박재보 | L34: 공통 | M34: 프로세스 개선 | N34: 공사비 | O34: [단기목표] 중고거래 APP개발을 통한 자재현황관리 및 공유 [중장기목표] 건축자재중고거래 e-커머스 사업(ex : 당근 플랫폼) | P34: [단기목표] ▪ 개선전 : 현장 잉여공사자재 및 가설자재, 사무실 집기류 등 관리 소홀에 따른 손실 ▪ 개선후 : APP(ex : 당근 플랫폼)을 통한 실시간 전현장 자재 현황 파악 가능하여 현장 대 현장 공유를 통해 신규 구입 방지 및 긴급 필요 자재 공유하여 현장 원가 리스크 감소 (협력사도 참여) [중장기목표] ▪ e-커머스 사업을 통해 타건설사 및 협력업체까지 공유하는 방식의 건축자재중고거래 를 통해 마켓쉐어 될 수 있는 중고거래시장 개척 (이익창출 및 브랜드 가치 상승_재사용을 통한 ESG 경영과도 부합) | Q34: O | R34: X | S34: 23 | T34: 56 | U34: 방향성, 아이디어는 좋으나 논의 결과 개발비 및 투입 인력 등 회사의 역량 부족. 현실적으로 어려움 | X34: 24년3분기(240920) | Z34: Case2. (인정O,채택X)피드백 완료
A35: 25 | B35: PR/P-TF-CE-1 | C35: 건축 | D35: 본사 | E35: 1502614 | F35: 과장 | G35: 건축지원팀 | H35: 민경민 | I35: 45474 | J35: 박재보, 박준용, 양창모 | K35: 박재보 | L35: 구매 | M35: 공통가설 | N35: 공사비 | O35: 동절기보양자재 지급자재 → 철콘업체 지입자재로 전환 | P35: • 철콘업체 지입자재로 입찰 진행 | Q35: X | S35: 14 | U35: 과거 지입자재에서 지급자재로 변경된 품목임. 건설경기 활황시, 수급문제와 철콘업체의 과도한 단가 요구 및 비위 문제로 지급자재로 운영중임. 과거 논의가 많이 되었던 건으로 아이디어로 인정하기 어려움 | Z35: Case1. (인정X)피드백 완료
A36: 26 | B36: CO/Z-PI-CE-2 | C36: 건축 | D36: 현장 | E36: 1502615 | F36: 과장 | G36: 원당1구역 재개발 | H36: 민승기 | I36: 45474 | J36: 차원재, 박재보, 고한울 | K36: 박재보 | L36: 공통 | M36: 프로세스 개선 | N36: 공사비 | O36: 착준공지원팀 신설로 착준공 지원 | P36: • (준공)‘24년 6개 / ‘25년 9개 / ‘26년 7개 준공 Risk 최소화 • (착공) 향후 수주 PJ 착수 지원 | Q36: X | S36: 12 | U36: 최근까지 수차례 논의 되었던 사안. 아이디어 제공자의 소속팀의 고유업무. 새로운 TOP아이디어로 인정되기 어려움 | Z36: Case1. (인정X)피드백 완료
A37: 27 | B37: CO/Z-PI-EXP-2 | C37: 건축 | D37: 본사 | E37: 1203784 | F37: 사원 | G37: 건축지원팀 | H37: 안혜림 | I37: 45474 | J37: 차원재, 박재보, 고한울 | K37: 박재보 | L37: 공통 | M37: 프로세스 개선 | N37: 전사경비 | O37: 캘린더, 다이어리 종류별 개별 신청 | P37: • 업무시스템 - 임직원공통 – 이벤트신청 메뉴를 활용한 개별신청으로, 현장 및 부서별 신청수량 조정이나 별도 취합이 필요 없음 | Q37: O | R37: X | S37: 20 | T37: 통합 (180번) | X37: 24년3분기(240920) | Z37: Case2. (인정O,채택X)피드백 완료
A38: 28 | B38: CO/Z-PI-EXP-3 | C38: 건축 | D38: 본사 | E38: 1300816 | F38: 과장 | G38: 외주팀 | H38: 이승현 | I38: 45474 | J38: 차원재, 박재보, 고한울 | K38: 박재보 | L38: 공통 | M38: 프로세스 개선 | N38: 전사경비 | O38: 노트북 3년 이상 사용으로 원가절감시, 렌탈비용 50%에 상응하는 복지포인트 지급 | P38: • 평소 노트북 관리를 통해 조기 렌탈 사용료 발생 방지 • 노트북 신청 주기 관리를 통한 원가 절감 달성시 렌탈 비용 50%에 상응 하는 복지포인트 지급 | Q38: X | S38: 9 | U38: 현재 렌탈로 운영되어 사용주기 초과하여도 원가절감 효과가 없음. 현황 파악이 잘 못되어 아이디어로 인정 어려움 | Z38: Case1. (인정X)피드백 완료
A39: 29 | B39: PR/C-PI-CE-1 | C39: 건축 | D39: 본사 | E39: 2202025 | F39: 차장 | G39: 건축지원팀 | H39: 이철호 | I39: 45474 | J39: 고한울, 박재보, 고한울 | K39: 고한울 | L39: 외주 | M39: 프로세스 개선 | N39: 공사비 | O39: 준공후 협력업체 정산프로세스 수립 | P39: • 준공 +1개월 : 협력업체 정산 계획 현황 서면 보고 • 준공 +2개월 : 미정산 협력업체 정산 협의 현황 및 계획 서면 보고 • 준공 +3개월 : 미정산 협력업체 정산 계획 사업부 대면 보고 (현장소장, 공사팀장, 공무팀장) → 필요시 협력업체 담당자 / 현장 / 유관부서(건축지원,외주外) 본사 회의 실시 현장설명서에 협력업체 정산 요청 방법 및 기한 관련 기준 추가 삽입 | Q39: O | R39: O | S39: 23 | T39: 통합 | U39: 하도급법 강화에 따른 협력사 정산 지연시 지연이자가 발생하여 당사 영영이익 감소에 큰 영향을 주고 있는 사안입니다. 프로세스 개선 및 업무 혁신을 통한 지연이자 최소화를 달성해야 합니다. 협력사와의 계약, 현장의 원가관리, 사업부 사업관리 등 많은 유관부서와의 연관성이 있는바, CFT 를 구성하여 종합적인 활동을 이끌어야 됩니다. | W39: N차(미정) | X39: 24년3분기(240920) | Z39: Case3. (인정O,채택 검토)피드백 완료 | AA39: 정산 프로세스 및 지연이자에 대한 검토사항입니다. (29번, 72번, 80번 유사함)
A40: 30 | B40: CO/D-A/F-CS-1 | C40: 건축 | D40: 본사 | E40: 0600053 | F40: 차장 | G40: 건축지원팀 | H40: 임양순 | I40: 45474 | J40: 안희진, 송원일, 김태용 | K40: 안희진 | L40: 수행-공사성 | M40: 건축_마감 | N40: 하자보수 | O40: 타일 뒷채움 부족 및 부착강도 하자소송비 저감 추진 | P40: • 외주(타일공사)공사 현장설명서 개정, “뒷채움 기준”, “피해에 대한 보상", “부착강도 기준” 등 • 외주(타일공사)공사 내역에 “타일 뒷채움 조사비”, “부착강도 시험비” 항목 신설 • 현장별 자료 보존 및 소송 時 활용 | Q40: O | R40: X | S40: 20 | T40: 통합 | X40: 24년3분기(240920) | Z40: Case2. (인정O,채택X)피드백 완료
A41: 31 | B41: CO/Z-ID/R-CE-1 | C41: 건축 | D41: 본사 | E41: 1202930 | F41: 차장 | G41: 건축지원팀 | H41: 정성훈 | I41: 45474 | J41: 차원재, 차원재, 박준용 | K41: 박재보 | L41: 공통 | M41: 민원처리비 | N41: 공사비 | O41: C.G.L 미수령 보험금 수령 및 업무R&R, 프로세스 개선 | P41: • 연도별 잔여 추산금 (Outstanding Loss) 中 준공현장 위주 즉시 회수 | Q41: O | R41: O | S41: 28 | T41: 90 | V41: O | W41: 3차(240909) | X41: 24년3분기(240920) | Y41: 24년3분기(240920) | Z41: Case4. (채택)피드백 완료
A42: 32 | B42: EN/I-A/F-CE-5 | C42: 건축 | D42: 본사 | E42: 1202930 | F42: 차장 | G42: 건축지원팀 | H42: 정성훈 | I42: 45474 | J42: 김태용, 송원일, 김태용 | K42: 김태용 | L42: 설계_건축내부 | M42: 건축_마감 | N42: 공사비 | O42: 공용부 습식공사 벽돌자재 변경 | P42: • 공동주택 기준층 공용부 습식공법 변경 • 기존 시멘트벽돌 → 변경 ALC블록 | Q42: O | R42: X | S42: 19 | T42: 58 | U42: (1차검토 : 미채택) 의미 있는 제안입니다. 하지만 실제 주거동 공용부 기준층에 조적벽체가 적용되는 사례는 ST 설치구간으로 극히 제한됩니다. 또한 지하층의 경우에도 주거동 승강기 홀 진입 복도에 적용되나, 이 또한 벽체 타일 마감에 있어 기존 시멘트 벽돌보다 신축줄눈 관리 등 시공 관리 포인트가 증가되어 현 시점에서는 과제화 사항에서 제외하였습니다. | X42: 24년3분기(240920) | Z42: Case2. (인정O,채택X)피드백 완료
A43: 33 | B43: CO/D-A/F-CE-2 | C43: 건축 | D43: 본사 | E43: 1202930 | F43: 차장 | G43: 건축지원팀 | H43: 정성훈 | I43: 45474 | J43: 안희진, 송원일, 김태용 | K43: 안희진 | L43: 수행-공사성 | M43: 건축_마감 | N43: 공사비 | O43: 균열 등 품질관리 로봇기술 도입 | P43: • 외벽도장, 골조품질(균열 등)관리, 외부 준공청소용 로봇기계기술 도입 | Q43: X | S43: 12 | U43: 미래지향적이긴 하나 단기에 적용할 만한 상용화된 기술이 없어 금회 채택되지 않았습니다. | Z43: Case1. (인정X)피드백 완료
A44: 34 | B44: CO/D-C-CE-1 | C44: 건축 | D44: 본사 | E44: 2201276 | F44: 과장 | G44: 건축지원팀 | H44: 조예술 | I44: 45474 | J44: 안희진, 박준용, 양창모 | K44: 박준용 | L44: 수행-공사성 | M44: 토목 | N44: 공사비 | O44: - 치환공사 표준 시공안 수립 | P44: • 현장 여건별 Case 구분하여 공사비, 공기 최적화 기준안 수립 • 착공 초기 공사용 장비 진입불가 기간 최소화 및 추후 정산시 합리적인 공사금액 반영 가능 | Q44: O | R44: X | S44: 20 | U44: 아이디어 인정, 과제 미채택 (아이디어 제안자 과제화 불필요 의견 수용) | X44: 24년3분기(240920) | Z44: Case2. (인정O,채택X)피드백 완료
A45: 35 | B45: PR/P-PI-CE-1 | C45: 건축 | D45: 본사 | E45: 0600047 | F45: 부장 | G45: 기술혁신팀 | H45: 김준우 | I45: 45474 | J45: 박재보, 박재보, 고한울 | K45: 박재보 | L45: 구매 | M45: 프로세스 개선 | N45: 공사비 | O45: 지급자재 관리 APP개발 및 지급자재 확대 | P45: • 지급자재 관리 APP 개발 및 복합개발 지급자재 확대 • 지급자재 전산화 System 개발을 통한 Loss 저감 | Q45: O | R45: X | S45: 20 | T45: 60 | U45: 아이디어는 인정되며 APP개발은 구체적이나 그 외 내용은 모호함 APP개발은 유관부서 협의결과 현실적으로 투자비는 예상치보다 훨씬 높으며 유니파이어와 연계가 불가피하나 실현가능성 낮음. (유니파이어 개발 시점에도 논의된적있으나 드랍) 업무적 편의 증대, 실제 절감 효과는 산출이 힘듬 그외 지급자재 확대 및 관리방안은 방향성만 있고 구체성이 부족 | X45: 24년3분기(240920) | Z45: Case2. (인정O,채택X)피드백 완료
A46: 36 | B46: EN/S-A/S-CE-2 | C46: 건축 | D46: 본사 | E46: 0600047 | F46: 부장 | G46: 기술혁신팀 | H46: 김준우 | I46: 45474 | J46: 박준용, 송원일, 박준용 | K46: 박준용 | L46: 구조/토목 | M46: 건축_골조 | N46: 공사비 | O46: 기초 우마 철근 등 보강근 -> 중공철근/GFRP | P46: • 기초 우마 철근 등 보강근 -> 중공철근/GFRP • 우마철근 및 보강용 철근 대체품 사용 | Q46: O | R46: X | S46: 20 | T46: 46 | U46: GFRP는 현시점에 건축 구조물에 적용은 어려우며, 강도대비 단가는 저렴하나, 우마 철근의 특성상 고강도를 요구하지 않으므로 경제성 확보가 어려움 | X46: 24년3분기(240920) | Z46: Case2. (인정O,채택X)피드백 완료
A47: 37 | B47: EN/I-A/F-CE-6 | C47: 건축 | D47: 본사 | E47: 2102764 | F47: 차장 | G47: 기술혁신팀 | H47: 박규선 | I47: 45474 | J47: 김태용, 송원일, 김태용 | K47: 김태용 | L47: 설계_건축내부 | M47: 건축_마감 | N47: 공사비 | O47: 빗물저수조/소화수조 천장 방수 삭제 | P47: • 빗물저수조/소화수조 천장 방수 삭제 • 안산 고잔연립 9구역 주택재건축 정비사업 : 외주비 5,900,000원 절감 | Q47: O | R47: X | S47: 23 | T47: 68 | U47: (1차검토 : 미채택) 제안 자체는 권장되어야 할 좋은 내용입니다. 다만, 최근 건식저수조 적용 사례가 점차 확대되는 추세이며 또한 각 현장별로 저수조 천정의 방수 삭제는 단순 선택으로 비교적 간단히 처리할 수 있는 사항이므로 과제화 항목에서는 제외하였습니다. | X47: 24년3분기(240920) | Z47: Case2. (인정O,채택X)피드백 완료
A48: 38 | B48: EN/S-C-CE-2 | C48: 건축 | D48: 본사 | E48: 2202067 | F48: 과장 | G48: 기술혁신팀 | H48: 김지민 | I48: 45474 | J48: 박준용, 박준용, 양창모 | K48: 박준용 | L48: 구조/토목 | M48: 토목 | N48: 공사비 | O48: 공장제작형 철근망(SP-CIP)을 활용한 CIP공사 원가절감 | P48: • 공장제작형 철근망(SP-CIP)을 활용한 CIP공사 원가절감 • 철근망 조립비 및 재료비 포함 재래식 공법대비 약 10%절감 Ex) 상인천초교 CIP철근망 재료+가공비 : 5억 -> STG800 적용시 4.5억 0.5억 절감 | Q48: O | R48: O | S48: 24 | T48: 75 | U48: 3차 과제승인위 상정완료 | V48: O | W48: 3차(240909) | X48: 24년3분기(240920) | Y48: 24년3분기(240920) | Z48: Case4. (채택)피드백 완료 | AA48: 통합 (Main)
A49: 39 | B49: EN/S-A/S-CE-3 | C49: 건축 | D49: 본사 | E49: 2203375 | F49: 대리 | G49: 기술혁신팀 | H49: 박현흠 | I49: 45474 | J49: 박준용, 송원일, 박준용 | K49: 박준용 | L49: 구조/토목 | M49: 건축_골조 | N49: 공사비 | O49: 공동주택 지하층 PIT 보+DECK 슬래브 적용 | P49: • 공동주택 지하층 PIT 보+DECK 슬래브 적용 • 공동주택 지하층 PIT 보+DECK 슬래브 적용을 통한 시공성 개선 및 원가절감 | Q49: O | R49: O | S49: 18 | T49: 73 | U49: 6차 과제승인위 상정완료 | V49: O | W49: 6차(241203) | X49: 24년3분기(240920) | Y49: 24년4분기(241220) | Z49: Case3. (인정O,채택 검토)피드백 완료
A50: 40 | B50: EN/S-A/S-CE-4 | C50: 건축 | D50: 본사 | E50: 1104091 | F50: 차장 | G50: 기술혁신팀 | H50: 백창현 | I50: 45474 | J50: 박준용, 송원일, 박준용 | K50: 박준용 | L50: 구조/토목 | M50: 건축_골조 | N50: 공사비 | O50: 지하주차장 압축기둥 다월철근 50% 적용 | P50: • 지하주차장 압축기둥 다월철근 50% 적용 • 지하주차장 기둥 다월철근 최적화를 통한 원가절감 | Q50: O | R50: O | S50: 30 | T50: 88 | U50: 2차 과제승인위 상정완료 | V50: O | W50: 2차(240829) | X50: 24년3분기(240920) | Y50: 24년3분기(240920) | Z50: Case4. (채택)피드백 완료 | AA50: 통합 (Main)
A51: 41 | B51: EN/S-A/S-CE-5 | C51: 건축 | D51: 본사 | E51: 1203416 | F51: 차장 | G51: 기술혁신팀 | H51: 최기영 | I51: 45474 | J51: 박준용, 송원일, 박준용 | K51: 박준용 | L51: 구조/토목 | M51: 건축_골조 | N51: 공사비 | O51: 공동주택 철근 강도 상향(D13 이하 철근 SD500) | P51: • 공동주택 철근 강도 상향(D13 이하 철근 / SD500) • 공동주택 D13이하 철근 SD500 적용을 통한 원가절감 | Q51: O | R51: X | S51: 30 | U51: 아이디어 인정, 과제 미채택(통합) TOP추진실 중점추진과제(공동주택 철근량 최적화)로 통합하여 진행예정이므로 아이디어만 인정하였습니다. | X51: 24년3분기(240920) | Z51: Case2. (인정O,채택X)피드백 완료 | AA51: 통합 (TOP) | AD51: ][
A52: 42 | B52: EN/S-A/S-CE-6 | C52: 건축 | D52: 본사 | E52: 2203374 | F52: 대리 | G52: 기술혁신팀 | H52: 최영후 | I52: 45474 | J52: 박준용, 송원일, 박준용 | K52: 박준용 | L52: 구조/토목 | M52: 건축_골조 | N52: 공사비 | O52: 주차장을 TR 기초 적용 | P52: • 주1을 TR 기초 적용 • 주1을 TR(Tapered Reinforced) 적용을 통한 원가절감 | Q52: X | S52: 11 | U52: 아이디어 미인정 해당기술은 원천기술 업체와 기술협약(적용실적에 따른 인센티브 수급)이 되어있는 아이템이므로 단순 설계적용 추진으로 아이디어 인정은 불가합니다. | Z52: Case1. (인정X)피드백 완료
A53: 43 | B53: EN/S-C-CE-3 | C53: 건축 | D53: 본사 | E53: 1700665 | F53: 과장 | G53: 기술혁신팀 | H53: 박대하 | I53: 45474 | J53: 박준용, 박준용, 양창모 | K53: 박준용 | L53: 구조/토목 | M53: 토목 | N53: 공사비 | O53: 초고강도 PHC 파일 적용 | P53: • 비용절감 효과 1) 파일 지지력 상향을 통한 파일 총 길이 저감 ① 저감 요소 : 지지력 상향을 통한 파일 개수 저감 ② 증가 요소 : 연암 정착으로 공당 정착 길이 증가 → 증가 요소보다 저감 기대 효가가 크며 원가 절감이 예상 됨. ※ 풍화대가 깊어 암반정착에 대한 소요 파일 길이가 과도할 것으로 예상될 경우 미적용 2) 벽체 하부 파일 1열 배치 시 추가적인 기초 두께 저감 예상 | Q53: O | R53: X | S53: 23 | T53: 55 | U53: 아이디어 인정, 과제 미채택 해당 설계법은 일반적인 구조설계 업무 최적화 기법이며, 기 시행중인 파일컨설팅 업무에 포함된 사항이므로 과제화는 불필요합니다. | X53: 24년3분기(240920) | Z53: Case2. (인정O,채택X)피드백 완료 | AA53: 중요한 과제이나 상인천초교 프로젝트 설계결과 접수 후 과제 구체화 예정
A54: 44 | B54: EN/I-A/F-CE-7 | C54: 기획 | D54: 본사 | E54: 1703079 | F54: 대리 | G54: 투자전략팀 | H54: 김진혁 | I54: 45474 | J54: 김태용, 송원일, 김태용 | K54: 김태용 | L54: 설계_건축내부 | M54: 건축_마감 | N54: 공사비 | O54: 욕실 바닥 단열재 스펙 다운을 통한 원가 절감 | P54: • 재료비 최소 약 1,000만원 절감 (1,000세대 기준 / 비드법 2종1호 -> 2종3호 기준) | Q54: O | R54: X | S54: 18 | T54: 57 | U54: (1차검토 : 미채택) 포레나 공동주택 표준 매뉴얼 기 정립사항 | X54: 24년3분기(240920) | Z54: Case2. (인정O,채택X)피드백 완료
A55: 45 | B55: EN/I-A/F-CE-8 | C55: 건축 | D55: 본사 | E55: 1202921 | F55: 과장 | G55: 기술혁신팀 | H55: 박찬기 | I55: 45474 | J55: 김태용, 송원일, 김태용 | K55: 김태용 | L55: 설계_건축내부 | M55: 건축_마감 | N55: 공사비 | O55: 공동주택 단열설계 최적화 방안 적용 | P55: • 공동주택 단열설계 최적화 방안 적용 포레나 단위세대 합리적 단열설계 변경을 통한 원가절감 | Q55: O | R55: X | S55: 19 | T55: 통합 (중점) | U55: (1차검토 : 중점과제와 통합) 제안하신 내용 중 다용도실을 난방구간으로 포함하는 부분은 적용이 가능할 것으로 판단됩니다. 주요 10개사 중 대우, GS, DL, 현대 등 점차 설계 적용 비율이 증가되고 있습니다. 단위세대 관련 타 제안과 통합하여 과제화 예정입니다. | X55: 24년3분기(240920) | Z55: Case2. (인정O,채택X)피드백 완료
A56: 46 | B56: EN/S-A/S-CE-7 | C56: 건축 | D56: 본사 | E56: 2100609 | F56: 대리 | G56: 기술혁신팀 | H56: 박종호 | I56: 45474 | J56: 박준용, 송원일, 박준용 | K56: 박준용 | L56: 구조/토목 | M56: 건축_골조 | N56: 공사비 | O56: 3D Shop 모델 운영 및 분석을 통한 원가상승 방지 | P56: • 3D 모델기반 철골공사 물량관리 • 3D Shop 모델 운영 및 분석을 통한 원가상승 방지 | Q56: O | R56: O | S56: 23 | T56: 84 | U56: 5차 과제승인위 상정완료 | V56: O | W56: 5차(241104) | X56: 24년3분기(240920) | Y56: 24년4분기(241220) | Z56: Case4. (채택)피드백 완료 | AA56: 통합 (Main)
A57: 47 | B57: EN/S-A/S-CE-8 | C57: 건축 | D57: 본사 | E57: 2002027 | F57: 차장 | G57: 기술혁신팀 | H57: 정성호 | I57: 45474 | J57: 박준용, 송원일, 박준용 | K57: 박준용 | L57: 구조/토목 | M57: 건축_골조 | N57: 공사비 | O57: BIM 기반 철근공사관리 (BIM기반 적산 및 웹 기반 철근공사관리 플랫폼 도입) | P57: • BIM 기반 철근공사관리 (BIM기반 적산 및 웹 기반 철근공사관리 플랫폼 도입) | Q57: O | R57: O | S57: 23 | T57: 81 | U57: 9차 과제승인위 상정완료 | V57: O | W57: 9차(250327) | X57: 24년3분기(240920) | Y57: 25년1분기(000000) | Z57: Case4. (채택)피드백 완료
A58: 48 | B58: EN/S-A/S-CE-9 | C58: 건축 | D58: 본사 | E58: 1000160 | F58: 차장 | G58: 기술혁신팀 | H58: 김정수 | I58: 45474 | J58: 박준용, 송원일, 박준용 | K58: 박재보 | L58: 구조/토목 | M58: 건축_골조 | N58: 공사비 | O58: H-MENT 확대 적용(수도권, 인프라 사업부) | P58: • H-MENT 확대 적용 추진 | Q58: O | R58: O | S58: 26 | T58: 80 | V58: O | W58: 5차(241104) | X58: 24년3분기(240920) | Y58: 24년4분기(241220) | Z58: Case4. (채택)피드백 완료
A59: 49 | B59: EN/S-A/F-CE-1 | C59: 건축 | D59: 본사 | E59: 2101159 | F59: 과장 | G59: 기술혁신팀 | H59: 구경모 | I59: 45474 | J59: 박준용, 송원일, 김태용 | K59: 박준용 | L59: 구조/토목 | M59: 건축_마감 | N59: 공사비 | O59: 콘크리트/모르타르 + 재활용 PET섬유 | P59: • 재활용PET섬유를 활용한 옥상무근모르타르의 생산시스템 구축 | Q59: O | R59: X | S59: 20 | T59: 67 | U59: 아이디어 인정, 과제 미채택 PET 섬유를 활용하는 아이디어 자체는 좋으나, PET섬유 주요수급원인 안전망이 PP소재로 적용중이라서 원자재 수급이 어렵다고 판단하여 아이디어만 인정하였습니다. | X59: 24년3분기(240920) | Z59: Case2. (인정O,채택X)피드백 완료
A60: 50 | B60: EN/E-E-CE-4 | C60: 건축 | D60: 현장 | E60: 0301109 | F60: 차장 | G60: 서울역 역세권 개발사업 호텔 | H60: 변세준 | I60: 45474 | J60: 오정화, 오정화, | K60: 오정화 | L60: 설계_전기 | M60: 전기 | N60: 공사비 | O60: 단위세대 통신수구 수량 최적화 | P60: • 단위세대 통신수구 수량 축소(14구→8구) • 추후 '초고속 정보통신 1등급 수준' 홍보는 불가함. 분양성 관련 사업팀 판단 필요 | Q60: X | S60: 12 | U60: 타사 사례 및 분양성을 고려했을때, 즉시 적용이 어려운 제안임 | Z60: Case2. (인정O,채택X)피드백 완료
A61: 51 | B61: EN/E-E-CE-5 | C61: 건축 | D61: 현장 | E61: 0301109 | F61: 차장 | G61: 서울역 역세권 개발사업 호텔 | H61: 변세준 | I61: 45474 | J61: 오정화, 오정화, | K61: 오정화 | L61: 설계_전기 | M61: 전기 | N61: 공사비 | O61: 홈네트워크 및 무인경비 공사범위 최적화 | P61: • 거실동체감지기,자석감지기,전자책도서관 삭제 • 홈넷카드수량축소(4개→2개) : 활용성 저하 | Q61: O | R61: X | S61: 24 | T61: 82 | U61: 향후, 재검토 | X61: 24년3분기(240920) | Z61: Case3. (인정O,채택 검토)피드백 완료
A62: 52 | B62: EN/E-E-CE-6 | C62: 건축 | D62: 현장 | E62: 0301109 | F62: 차장 | G62: 서울역 역세권 개발사업 호텔 | H62: 변세준 | I62: 45474 | J62: 오정화, 오정화, | K62: 오정화 | L62: 설계_전기 | M62: 전기 | N62: 공사비 | O62: IoT보안솔루션(OTP보안) 삭제 | P62: • IoT보안솔루션(OTP보안)삭제 : 개정법규적용에 의한 이중화구성으로 삭제 가능하다고 판단됨 | Q62: O | R62: X | S62: 24 | T62: 통합 (51번) | U62: 51번 제안과 통합 | X62: 24년3분기(240920) | Z62: Case2. (인정O,채택X)피드백 완료
A63: 53 | B63: EN/E-E-CE-7 | C63: 건축 | D63: 본사 | E63: 1300253 | F63: 과장 | G63: 건축전기팀 | H63: 김재구 | I63: 45474 | J63: 오정화, 오정화, | K63: 오정화 | L63: 설계_전기 | M63: 전기 | N63: 공사비 | O63: 전력간선 스펙 다각화(알루미늄 합금케이블) | P63: • (당초) 구리 케이블 → (변경) 구리 케이블, 알루미늄 합금 케이블 - 사업승인이전현장 또는 최초 도급 제안현장 적용가능 (구리케이블로 사업승인득한 현장은 변경 어려움. 조합 및 감리원 설득필요) | Q63: O | R63: O | S63: 28 | T63: 91 | V63: O | W63: 1차(240822) | X63: 24년3분기(240920) | Y63: 24년3분기(240920) | Z63: Case4. (채택)피드백 완료
A64: 54 | B64: EN/E-E-CE-8 | C64: 건축 | D64: 본사 | E64: 1300253 | F64: 과장 | G64: 건축전기팀 | H64: 김재구 | I64: 45474 | J64: 오정화, 오정화, | K64: 오정화 | L64: 설계_전기 | M64: 전기 | N64: 공사비 | O64: 무인택배 시스템 최적화 | P64: • 무인택배시스템 설계 기준 최적화 진행 - 당사 FORENA 브랜드 품질저하 이슈 나오지 않는 수준 검토 - 타사 동향 파악하여 적용개소 설정 • 적용 예정안 - 무인택배 시스템 적용개소 축소 : (당초) 각 동 1개소, 전체 세대의 15% 수준 적용 → (변경) 주ㆍ부 출입구 인근 동에 적용(2~3개소), 전체 세대의 6~8% 수준 적용 | Q64: O | R64: X | S64: 21 | T64: 63 | U64: 일괄 삭제 또는 최적화(수량 최소화)와 관련하여 사업팀 협의가 필요한 제안임. 추후 재검토 예정 | X64: 24년3분기(240920) | Z64: Case2. (인정O,채택X)피드백 완료
A65: 55 | B65: EN/E-E-CE-9 | C65: 건축 | D65: 본사 | E65: 1300253 | F65: 과장 | G65: 건축전기팀 | H65: 김재구 | I65: 45474 | J65: 오정화, 오정화, | K65: 오정화 | L65: 설계_전기 | M65: 전기 | N65: 공사비 | O65: 대기전력 차단장치(스위치, 콘센트) 최적화 | P65: • 대기전력 자동차단장치 설계 기준 최적화 진행 - 당사 FORENA 브랜드 품질저하 이슈 나오지 않는 수준 검토 - 타사 동향 파악하여 적용개소 설정 • 적용 예정안 - 단위세대 적용개소 축소 : (당초) 거실, 안방, 각방, 주방 +지역조례 → (변경) 거실, 안방, 각방 외 미적용 - 주민공동시설, 근린생활시설 미적용 | Q65: O | R65: X | S65: 25 | T65: 통합 (215) | U65: 215번 제안과 통합 | X65: 24년3분기(240920) | Z65: Case2. (인정O,채택X)피드백 완료
A66: 56 | B66: EN/E-E-CE-10 | C66: 건축 | D66: 본사 | E66: 2202059 | F66: 과장 | G66: 건축전기팀 | H66: 권창재 | I66: 45474 | J66: 오정화, 오정화, | K66: 오정화 | L66: 설계_전기 | M66: 전기 | N66: 공사비 | O66: 스마트 복합 살균조명 옵션 상품 개발 | P66: • 스마트 복합 살균조명 옵션 상품개발로 수익창출 • 일반가구(신발장 하부), 주방가구(상1갑 하부) 등의 간접조명을 살균조명 기능이 반영된 제품 • IOT App연동을 통한 원격제어 기능을 추가하여 살균기능 제어 기능 추가(ON/OFF 시간설정) | Q66: O | R66: X | S66: 18 | T66: 20 | U66: 구체적인 개발방향성에 대한 검토 및 옵션수요에 대한 디자인팀 협의 필요. 추후 진행 예정 | X66: 24년3분기(240920) | Z66: Case2. (인정O,채택X)피드백 완료
A67: 57 | B67: EN/M-M-CE-2 | C67: 건축 | D67: 본사 | E67: 0601384 | F67: 차장 | G67: 건축기계팀 | H67: 박민희 | I67: 45474 | J67: 박병규, 박병규, | K67: 박병규 | L67: 설계_기계 | M67: 기계 | N67: 공사비 | O67: 임시소방시설 연간단가 및 리사이클(Recycling) 시행 | P67: • 임시소방시설 재활용 위한 연간단가 및 업체선정 - 현장 종료 후 소화기, 간이소화장치의 외관 보수, 기능 보증 등을 통하여 신규 현장에 재활용 - 재활용이 불가능한 파손된 제품은 신규로 구입 / 전체 제품 중 약50% 재활용 가능 추정 | Q67: O | R67: O | S67: 26 | T67: 84 | V67: O | W67: 2차(240829) | X67: 24년3분기(240920) | Y67: 24년3분기(240920) | Z67: Case4. (채택)피드백 완료
A68: 58 | B68: CO/D-M-CE-1 | C68: 건축 | D68: 본사 | E68: 0601384 | F68: 차장 | G68: 건축기계팀 | H68: 박민희 | I68: 45474 | J68: 안희진, 박병규, | K68: 박병규 | L68: 수행-공사성 | M68: 기계 | N68: 공사비 | O68: 기계실 고중량 배관 가대 적용(용접삭제) | P68: • 기계실 상부 고중량 배관용 가대 적용(시공기준 재정립) 고중량용 배관 가대를 적용하여 기계실 내 용접작업 삭제 용접작업 삭제로 화재 위험 감소 | Q68: O | R68: X | S68: 24 | T68: 68 | U68: 시공성 개선은 확실하나 원가절감 부분 검토 필요(원가절감X) | Z68: Case3. (인정O,채택 검토)피드백 완료
A69: 59 | B69: CO/Z-M-CE-1 | C69: 건축 | D69: 본사 | E69: 1105017 | F69: 차장 | G69: 잠실MICE TFT | H69: 조영수 | I69: 45474 | J69: 차원재, 박병규, | K69: 차원재 | L69: 공통 | M69: 기계 | N69: 공사비 | O69: 접이식 스크린 방화셔터 | P69: • 접이식 스크린 방화셔터의 경우 방화 스크린을 두개 이상 적용하는 경우 혹은 ㄱ자 벽면처럼 일정한 각도를 두어 배치하는 경우 스크린이 펼쳐진 상태에서는 외부 화염 발생 시 구조적인 강직성이 약하여 스크린 사이로 화염이나 연기가 통과될 수 있는 위험을 대응할 수 있음. 1. ㄱ자형 벽면의 방화구획 확보 가능 2. 자유로운 각도 및 곡선형 셔터 설치 가능 3. ㄱ자 접합부위 무기둥으로 시공이 가능하여 넓은 시야 확보 가능 | Q69: O | R69: X | S69: 18 | U69: 인증완료된 이후 적용가능 현장 있을 경우 진행할 예정입니다. | X69: 24년3분기(240920) | Z69: Case3. (인정O,채택 검토)피드백 완료 | AA69: 윤기윤
A70: 60 | B70: EN/M-M-CE-3 | C70: 건축 | D70: 본사 | E70: 1105017 | F70: 차장 | G70: 잠실MICE TFT | H70: 조영수 | I70: 45474 | J70: 박병규, 박병규, | K70: 박병규 | L70: 설계_기계 | M70: 기계 | N70: 공사비 | O70: 계단실 급기 가압 방식의 댐퍼 시스템 | P70: • 특별피난계단의 계단실 및 비상용 승강장에 급기가압 제연설비가 설치되어야 하나, 신기술 도입 및 공사비 절감을 위해 계단실을 풍도로 사용하는 계단실 가압 방식을 적용하고자 함. | Q70: X | S70: 17 | U70: 새로운 제연 가압방식으로 소방방재청 승인 필요 | Z70: Case1. (인정X)피드백 완료
A71: 61 | B71: EN/M-M-CE-4 | C71: 건축 | D71: 본사 | E71: 1105017 | F71: 차장 | G71: 잠실MICE TFT | H71: 조영수 | I71: 45474 | J71: 박병규, 박병규, | K71: 박병규 | L71: 설계_기계 | M71: 기계 | N71: 공사비 | O71: 지하침출수 열원활용방안 | P71: • 영구배수 및 지하침출수를 우수조, 중수조에 저장하여 히트펌프를 통한 냉난방 열원으로 이용 1. 냉난방요금 절약 2. 하수도 요금 절약(광역시 이상) 3. 사수방지 제품 미필요 | Q71: O | R71: 검토중 | S71: 18 | T71: 차후진행 | U71: 잠실 마이스 TFT의견으로 현장 특수성 및 구체적인 방법 제안 필요 | X71: 24년3분기(240920) | Z71: Case3. (인정O,채택 검토)피드백 완료
A72: 62 | B72: CO/I-TF-CE-6 | C72: 건축 | D72: 본사 | E72: 1105017 | F72: 차장 | G72: 잠실MICE TFT | H72: 조영수 | I72: 45474 | J72: 양창모, 박준용, 양창모 | K72: 양창모 | L72: 수행-비공사성 | M72: 공통가설 | N72: 공사비 | O72: 비콘을 이용한 근로자 안전관리방안 | P72: 1.안전모 스마트태그 부착으로 작업자 위치확인 2.중장비 비콘설치를 통한 접근시 경고알람 송출 등 3.현장상황에 따라서 접근시 위험이 예상되는 지하 피트층이나, 최상층 단부 등 위험지역을 별도 설정해서 사전에 허가된 근로자만 출입에 제한한 방식을 다양한 방법으로 근로자의 동선 및 작업관리 | Q72: O | R72: X | S72: 21 | T72: 57 | U72: 일부 내용 수정 및 재검토하여 과제화여부 재판단하겠음. | X72: 24년3분기(240920) | Z72: Case2. (인정O,채택X)피드백 완료 | AA72: 1040
A73: 63 | B73: EN/M-M-CE-5 | C73: 건축 | D73: 본사 | E73: 1300815 | F73: 과장 | G73: 건축기계팀 | H73: 최중현 | I73: 45474 | J73: 박병규, 박병규, | K73: 박병규 | L73: 설계_기계 | M73: 기계 | N73: 공사비 | O73: 지하 펌핑배수배관 재질변경(강관⇒PVC) | P73: • 열전도율이 낮은 PVC재질로 변경에 따른 결로 발생현상 피해 저하 • 시공성 향상에 따른 인건비 절감 가능 • 타 사 적용 현장 확인/ 검증 후 당 사 기준 정립 | Q73: O | R73: O | S73: 20 | T73: 71 | V73: O | W73: 7차(250114) | X73: 24년3분기(240920) | Y73: 25년1분기(250421) | Z73: Case4. (채택)피드백 완료
A74: 64 | B74: EN/M-M-CE-6 | C74: 건축 | D74: 본사 | E74: 1803686 | F74: 대리 | G74: 건축기계팀 | H74: 최호영 | I74: 45474 | J74: 박병규, 박병규, | K74: 박병규 | L74: 설계_기계 | M74: 기계 | N74: 공사비 | O74: 단위세대 난방코일피치 기준 재정립 | P74: 단위세대 침실 난방코일피치 기준 재정립 (당초) 200mm → (변경) 230mm | Q74: O | R74: O | S74: 25 | T74: 83 | V74: O | W74: 3차(240909) | X74: 24년3분기(240920) | Y74: 24년3분기(240920) | Z74: Case4. (채택)피드백 완료
A75: 65 | B75: PR/C-E-CE-1 | C75: 건축 | D75: 해외 | E75: 1104094 | F75: 차장 | G75: 건축지원팀(파견) | H75: 오정수 | I75: 45474 | J75: 고한울, 오정화, | K75: 오정화 | L75: 외주 | M75: 전기 | N75: 공사비 | O75: 핵심공종(ELEV) 실 투입기간을 계약기간으로 적용 / 공종관리 진행 | P75: 실제 하도급 투입기간을 하도급 계약기간으로 적용 - 계약 미이행 시 패널티 부여 - 공종관리 및 정산에 따른 투명한 정산/투입으로 분쟁 및 지연이자 최소화 - 적정 투입 인원 및 자재 납품을 계약기간으로 명기 - 1대당/일로 지연/돌관비용 적용하여 계약진행 _ 하도급 정산의 증감을 명확화 원인 명확화에 따른 지연사유 및 돌관비용 집행 명확화 - 선행공종 지연에 따른 1대당/일로 지연/돌관비용 적용하여 계약진행 - 잡업인원 미투입에 따른 업체 패널티 부여 - 공종관리 및 정산에 따른 투명한 정산/투입으로 분쟁 및 지연이자 최소화 | Q75: O | R75: X | S75: 23 | T75: 76 | U75: 외주팀에서 승강기 연간단가 검토중. CFT 구성하여, 명확한 기준 수립을 통해 공사수행을 원활하게 하고, 불필요한 분쟁을 최소화 할수 있도록 연간단가 계약조건 검토 요망 | X75: 24년3분기(240920) | Z75: Case2. (인정O,채택X)피드백 완료
A76: 66 | B76: EN/E-E-CE-11 | C76: 건축 | D76: 해외 | E76: 1104094 | F76: 차장 | G76: 건축지원팀(파견) | H76: 오정수 | I76: 45474 | J76: 오정화, 오정화, | K76: 오정화 | L76: 설계_전기 | M76: 전기 | N76: 공사비 | O76: 공용부전기 사용실태 분석을 통한 최적설계방안 수립 | P76: 공용변압기 이용율 미확인 : 전기 예상부하용량에 수용율을 적용한 변압기 용량 선정 - 변압기 용량에 따른 케이블 굵기 및 차단기 선정 - 원자재값 상승에 따른 자재비 및 시공 공사비 원가 증가 - 입주민 공용전기료금 금액 증가 • 포레나 준공단지 전기부하 사용량에 따른 변압기 및 케이블 원가절감 추진 전력계통영향평가 미적용에 따른 사업비 및 인허가 단축 - 약 2,000~2000세대 이상 전기 예상 계약용량 10MW - 변압기 용량 최적화 설계로 전기 계약용량 | Q76: O | R76: O | S76: 26 | T76: 88 | V76: O | W76: 2차(240829) | X76: 24년3분기(240920) | Y76: 24년3분기(240920) | Z76: Case4. (채택)피드백 완료
A77: 67 | B77: EN/E-E-CE-12 | C77: 건축 | D77: 해외 | E77: 1104094 | F77: 차장 | G77: 건축지원팀(파견) | H77: 오정수 | I77: 45474 | J77: 오정화, 오정화, | K77: 오정화 | L77: 설계_전기 | M77: 전기 | N77: 공사비 | O77: 안면인식 로비폰 적용 | P77: 실물키의 휴대 불편함 및 분실의 위험이 없는 안면인식 로비폰(제안) - 원가절감 및 입주민 공동출입구 출입 보안강화 아이템으로 적용 검토함 • (기타) 스마트 언텍스(Untact) 기술 도입으로 보안성 강화 및 원가절감 - 스마트 원패스키(스마트폰APP)은 동일 하게 적용 - 실물형 카드 및 원패스 키 삭제 - 아파트 동출입구에 안면인식 출입기 적용을 통한 보안성 강화 | Q77: X | S77: 15 | U77: 기 품의 완료된 건으로, 원가절감 여부에 대한 재검토가 필요합니다. (원패스키 삭제가 건축전기팀 품의 '스마트파킹시스템 개선안'에도 중복적용 되어있음) | Z77: Case1. (인정X)피드백 완료
A78: 68 | B78: CO/I-TF-CE-7 | C78: 건축 | D78: 해외 | E78: 1104094 | F78: 차장 | G78: 건축지원팀(파견) | H78: 오정수 | I78: 45474 | J78: 양창모, 박준용, 양창모 | K78: 양창모 | L78: 수행-비공사성 | M78: 공통가설 | N78: 공사비 | O78: 안면인식 건강관리 시스템 활용 | P78: • 안면인식 건강관리 시스템 활용 - 근로자 건강광리를 통한 우발 손실 제외 코로나 및 근로환경의 더위 등에 따른 근로자 건강관리 중요 - 근로자 개인질병의 사망 시에도 인적/물적 손해 발생 - 신규채용자 교육시 개인의 건상상태 확인 / 체크 | Q78: X | S78: 11 | U78: 아이디어는 참신하나 시스템의 정확도에 따른 활용도 관련검토가 추가적으로 필요하여 금번에는 미채택 하였습니다. | Z78: Case1. (인정X)피드백 완료
A79: 69 | B79: EN/E-E-CE-13 | C79: 건축 | D79: 해외 | E79: 1104094 | F79: 차장 | G79: 건축지원팀(파견) | H79: 오정수 | I79: 45474 | J79: 오정화, 오정화, | K79: 오정화 | L79: 설계_전기 | M79: 전기 | N79: 공사비 | O79: 공동주택 단위세대 조명밀도 5.5W/m2 이하 기준 마련 | P79: • 단위세대 별 조명밀도 기준 강화 (現 6.49[W/㎡] → 5.25[W/㎡])) - 선제적인 설계 대응을 통한 신재생에너지 시공원가 절감 - 분양가 경쟁력 확보 등 기준 마련 단위세대 조명밀도 절감에 따른 친환경 주택 법규 대응 / 시공성 향상 - ZEB(제로에너지건축물) 정책에 따른 기본 대응방안 마련 - 에너지절약형 친환경주택 건설기준(국토교통부) 대응 - 원가절감(재료비 + 신재생에너지 투입비) 및 시공성 향상 | Q79: O | R79: X | S79: 27 | T79: 80 | U79: (CFT 구성 및 과제정의서 작성중) 디자인팀, 구매팀 협업 진행예정 (디자인검토 및 기존 연간단가 변경계약 관련사항 등) | V79: O | X79: 24년3분기(240920) | Z79: Case2. (인정O,채택X)피드백 완료
A80: 70 | B80: EN/E-E-CE-14 | C80: 건축 | D80: 해외 | E80: 1104094 | F80: 차장 | G80: 건축지원팀(파견) | H80: 오정수 | I80: 45474 | J80: 오정화, 오정화, | K80: 오정화 | L80: 설계_전기 | M80: 전기 | N80: 공사비 | O80: 공동주택 공용부조명 연단가 진행 | P80: • 등기구 상품 종류 축소 및 시공방안 획일화를 통한 시공성 향상 및 원가절감 - 2024년 어워드 출품 및 2024년 현장 첫 적용으로 원가절감 진행 등기구 디자인 및 시공방법 단순화 - 타공종 간섭사항 최소화 _ 시공성 향상 - 등기구 수량 최소화 _ 원가경쟁력 확보 및 시공성 향상 - 상가 등 타공/보강 등 건축 폐기물 미발생 | Q80: X | S80: 13 | U80: 기 품의완료 및 현장 적용중인 사항으로, 제안 인정 불가합니다. | Z80: Case1. (인정X)피드백 완료
A81: 71 | B81: EN/E-E-CE-15 | C81: 건축 | D81: 해외 | E81: 1104094 | F81: 차장 | G81: 건축지원팀(파견) | H81: 오정수 | I81: 45474 | J81: 오정화, 오정화, | K81: 오정화 | L81: 설계_전기 | M81: 전기 | N81: 공사비 | O81: 공동주택 APP 상품 _ IoT 디바이스 업체 APP 도입으로 원가절감 공동주택 H/N 제어 및 커뮤니티 APP 외주화 | P81: • 2020년 FORENA APP 개발 / 적용 후 업데이트 미수행 _ 경쟁력 약화 • 분양세대수 하락에 따라 개발비 투입원가 증가 • 부동산 경기 하락에 따른 분양물량 저하 _ 포레나 APP 업데이트 미진행 • 삼성전자, 삼성물산 등 IoT APP 외주화에 따른 원가절감 추진 | Q81: O | R81: O | S81: 23 | T81: 76 | U81: FORENA APP 업데이트에 필요한 금액 확인 및 삼성물산(홈닉), 현대통신 등 원가경쟁력 갖춘 업체와 금액 비교 검토 필요합니다. | V81: O | W81: 5차(241104) | X81: 24년3분기(240920) | Y81: 24년4분기(241220) | Z81: Case3. (인정O,채택 검토)피드백 완료
A82: 72 | B82: PR/C-PI-CE-2 | C82: 건축 | D82: 해외 | E82: 1104094 | F82: 차장 | G82: 건축지원팀(파견) | H82: 오정수 | I82: 45474 | J82: 고한울, 박재보, 고한울 | K82: 고한울 | L82: 외주 | M82: 프로세스 개선 | N82: 공사비 | O82: 공탁 / 간접비 사전 정산 진행 프로세스 확립 (지연이자 절감) | P82: 정산 합의 지연에 따른 지연이자 절감 방안 모색 - 정산 합의 지연에 따른 현장 정산금액 공탁 등의 집행 (실정보고 이후) - 간접비의 경우 2달이내 집행 정산 합의 지연에 따른 지연이자 절감 방안 모색 - 정산 합의 지연에 따른 현장 정산금액 공탁 등의 집행 (실정보고 이후) - 간접비의 경우 2달이내 집행 | Q82: O | R82: X | S82: 23 | T82: 통합 (29번) | U82: (채택 불인정) "준공후, 협력업체 정산프로세스 수립_이철호 2갑"과 목적은 유사하나 방법이 상이함. 논의 후 진행 | X82: 24년3분기(240920) | Z82: Case2. (인정O,채택X)피드백 완료 | AA82: 정산 프로세스 및 지연이자에 대한 검토사항입니다. (29번, 72번, 80번 유사함)
A83: 73 | B83: PR/C-E-CE-2 | C83: 건축 | D83: 해외 | E83: 1104094 | F83: 차장 | G83: 건축지원팀(파견) | H83: 오정수 | I83: 45474 | J83: 고한울, 오정화, | K83: 오정화 | L83: 외주 | M83: 전기 | N83: 공사비 | O83: 무선통신보조설비 설계 표준화 및 연단가 금액 구축 (공동주택) | P83: • 공동주택 무선통신보조설비 설계 표준화 및 연단가 금액 구축 - 공동주택의 경우 시스템적/금액적 이슈사항 없음 _ 연단가 업체 선정 - 분리발주의 경우 해당업체 연단가 금액으로 도급계약 유도 및 업체 관리 - 업체 관리 및 A/S 용이 | Q83: O | R83: X | S83: 19 | T83: 61 | U83: 설계 및 내역 표준화는 가능하나, 발주 가능한 분양예정 물량이 많지 않아, 즉각적인 연단가 업체선정 입찰진행은 어려울것으로 예상됨 | X83: 24년3분기(240920) | Z83: Case2. (인정O,채택X)피드백 완료
A84: 74 | B84: EN/E-E-CE-16 | C84: 건축 | D84: 해외 | E84: 1104094 | F84: 차장 | G84: 건축지원팀(파견) | H84: 오정수 | I84: 45474 | J84: 오정화, 오정화, | K84: 오정화 | L84: 설계_전기 | M84: 전기 | N84: 공사비 | O84: 전기실 무패드 및 지하주1을 천정형 스피커 적용 | P84: • 타 공종 간섭 최소화로 시공성 향상 및 건축 원가 절감 - 전기실 무패드 적용 (단, 전기실 바닥 FL이 지하주1을보다 낮은경우 제외) - 지하주1을 기둥에 적용하는 스피커 → 천정형으로 적용 (시공성 향상) | Q84: O | R84: X | S84: 22 | T84: 통합 (354번) | U84: 354번 제안과 통합(전기실 무패드) 지하주1을 천정형 스피커는 기 적용중임 | V84: O | X84: 24년3분기(240920) | Z84: Case2. (인정O,채택X)피드백 완료
A85: 75 | B85: EN/E-E-CE-17 | C85: 건축 | D85: 해외 | E85: 1104094 | F85: 차장 | G85: 건축지원팀(파견) | H85: 오정수 | I85: 45474 | J85: 오정화, 오정화, | K85: 오정화 | L85: 설계_전기 | M85: 전기 | N85: 공사비 | O85: 무인택배 삭제 및 신규 옵션상품 개발 (엘리베이터홀 CCTV 옵션 적용) | P85: • 공동주택 무인택배 삭제 + 엘리베이터홀 CCTV 옵션 - 무인택배 이용율 저하 (쿠팡배송 및 냉동식품 새벽배송 등) - AI 카메라 등 상품개발에 따른 상품성 강화 연계 | Q85: O | R85: X | S85: 21 | T85: 63 | U85: 일괄 삭제 또는 최적화(수량 최소화)와 관련하여 사업팀 협의가 필요한 제안임. 추후 재검토 예정 | X85: 24년3분기(240920) | Z85: Case2. (인정O,채택X)피드백 완료
A86: 76 | B86: CO/Z-E-CE-1 | C86: 건축 | D86: 해외 | E86: 1104094 | F86: 차장 | G86: 건축지원팀(파견) | H86: 오정수 | I86: 45474 | J86: 차원재, 오정화, | K86: 오정화 | L86: 공통 | M86: 전기 | N86: 공사비 | O86: 전기차 충전설비 최적설계 및 그룹 Synergy 강화 아이템 발굴 | P86: • 단지 외부(내부) 전기차 충전 스테이션 적용 - 지하주1을 적용 대비 소방 시설물(방화구획/소화설비) 절감 - 외부 지붕 구주몰 디자인 기획 / 조경상품 개발 연계 • 지하주1을 과금형 콘센트 적용을 통한 원가절감 추진 - 과금형콘센트의 경우 완속충전기로 인정 - 완속충전기 대비 50~70만원/대당 절감 x 주1을면수의 7% • 그룹 및 포레나 상품 상징성 - 외부 구조물 태양광 연계 _ 환경 친화적 & 공용전기료 절감 - 에너지 모니터링 설비 도입을 통한 기기 오작동, 차단 및 AS 연계 (w/한화 모티브) | Q86: O | R86: X | S86: 20 | T86: 통합 (299번) | U86: 299번 항목과 통합 | X86: 24년3분기(240920) | Z86: Case2. (인정O,채택X)피드백 완료
A87: 77 | B87: CO/Z-E-CE-2 | C87: 건축 | D87: 해외 | E87: 1104094 | F87: 차장 | G87: 건축지원팀(파견) | H87: 오정수 | I87: 45474 | J87: 차원재, 오정화, | K87: 오정화 | L87: 공통 | M87: 전기 | N87: 공사비 | O87: H²-EMS (Hanwha - Energy Management System) 구축 | P87: • 에너지절감, 사용자 편의성 향상, 관리비절감의 Intelligent System 도입 必 - BEMS, 자동제어, 전력제어, 조명제어, 원격검침 + 신재생에너지 통합 - 면허(통신면허) 관련 이슈 해결 및 일원화 관리로 공정관리 진행 | Q87: X | S87: 15 | U87: 공종간 업무스코프 정리가 필요한 사항입니다. | Z87: Case2. (인정O,채택X)피드백 완료
A88: 78 | B88: EN/E-E-CE-18 | C88: 건축 | D88: 해외 | E88: 1104094 | F88: 차장 | G88: 건축지원팀(파견) | H88: 오정수 | I88: 45474 | J88: 오정화, 오정화, | K88: 오정화 | L88: 설계_전기 | M88: 전기 | N88: 공사비 | O88: TV 및 방송자재 등 장비성 연단가 납품/시공 | P88: - TV 헤드앤드, 방송 앰프 등 전문성 자재의 설계 표준화 / 내역화 진행 | Q88: O | R88: X | S88: 19 | T88: 61 | U88: 설계 및 내역 표준화는 가능하나, 발주 가능한 분양예정 물량이 많지 않아, 즉각적인 연단가 업체선정 입찰진행은 어려울것으로 예상됨 | X88: 24년3분기(240920) | Z88: Case2. (인정O,채택X)피드백 완료
A89: 79 | B89: CO/I-TF-CE-8 | C89: 건축 | D89: 해외 | E89: 1104094 | F89: 차장 | G89: 건축지원팀(파견) | H89: 오정수 | I89: 45474 | J89: 양창모, 박준용, 양창모 | K89: 양창모 | L89: 수행-비공사성 | M89: 공통가설 | N89: 공사비 | O89: 대형 복합시설 공사 수행과정 푸드테크 도입 (생산성 향상 목적) | P89: • 삼성물산 평택 반도체 공장 등 벤치마킹 진행 - 근로자 식사, 휴식 및 화장실 공간의 제공을 통한 생산성 향상 • 푸드테크(커피바리스타 로봇 등) - 공동주택 커뮤니티 적용 등을 통한 상품성 강화 및 마케팅활용 _ 그룹 스마트 상품 - 대형복합 건설현장 도입을 통한 고품질의 서비스 제공 | Q89: X | S89: 6 | U89: 아이디어는 참신하나 생산성과 원가투입간 관련검토가 추가적으로 필요하여 금번에는 미채택 하였습니다. | Z89: Case1. (인정X)피드백 완료
A90: 80 | B90: PR/C-PI-CE-3 | C90: 건축 | D90: 본사 | E90: 1000208 | F90: 차장 | G90: 그린솔루션TFT | H90: 제은수 | I90: 45474 | J90: 고한울, 박재보, 고한울 | K90: 고한울 | L90: 외주 | M90: 프로세스 개선 | N90: 공사비 | O90: 지연이자 최소화(정산) | P90: 현장 정산 예상 금액의 80%(변동 가능) 선에서 先 변경계약 및 집행 後 정산 품의 정상 진행 - 예상금액/러프한 자료 수준으로 본부 지원팀 先 품의 후 현재와 같은 백데이터 증빙 추가 재품의 - 지급 이후에도 노무비닷컴을 통한 기성금의 관리가 가능함 - 하도급 업체에서 미동의시 법원 공탁처리를 통한 지연이자 증가 방지 | Q90: O | R90: X | S90: 23 | T90: 통합 (29번) | U90: (채택 불인정) "준공후, 협력업체 정산프로세스 수립_이철호 2갑"과 목적은 유사하나 방법이 상이함. 논의 후 진행 | X90: 24년3분기(240920) | Z90: Case2. (인정O,채택X)피드백 완료 | AA90: 정산 프로세스 및 지연이자에 대한 검토사항입니다. (29번, 72번, 80번 유사함)
A91: 81 | B91: CO/Z-YY-CE-1 | C91: 건축 | D91: 본사 | E91: 1000208 | F91: 차장 | G91: 그린솔루션TFT | H91: 제은수 | I91: 45474 | J91: 차원재, 고한울, 박재보 | K91: 박재보 | L91: 공통 | M91: 현장관리비 | N91: 공사비 | O91: Half Time 현채직 신설 | P91: • Half Time 현채직 신설 - 오전근무 / 오후근무 / 10시~15시 근무 등 유연한 Half Time 현채직 채용 신설 • 현장 준공시 필요 인원 증원 - 평상시 인건비 절감분으로, 준공 등 추가 인원 필요시 증원 | Q91: O | R91: X | S91: 19 | T91: 53 | U91: (건축지원팀, 인사기획팀 협의 완료) 아이디어로는 인정하였으나 현실적인 노무리스크, 인력출력에 대한 관리 문제로 유관부서 협의 후 불채택 되었습니다. 현장 여건 상, 안전사고의 우려 / 관리 포인트의 증가 등으로 인해 사업부에는 효용보다는 제한사항이 많을 것으로 판단됩니다 | X91: 24년3분기(240920) | Z91: Case2. (인정O,채택X)피드백 완료
A92: 82 | B92: PR/C-ID/H-CE-1 | C92: 건축 | D92: 본사 | E92: 1000208 | F92: 차장 | G92: 그린솔루션TFT | H92: 제은수 | I92: 45474 | J92: 고한울, 박재보, 안희진 | K92: 고한울 | L92: 외주 | M92: 안전관리비 | N92: 공사비 | O92: 하도급 업체 안전관리비 투입금액 명확화 | P92: 발주시 직공비화 후 변경계약 - 발주시 안전난간대, 추락방지망, 안전관리자 투입MM 등 직공비 내역화 입찰 - 낙찰 후 해당 금액 직공비에서 감액 및 안전관리비 증액 | Q92: O | R92: X | S92: 22 | T92: 통합 | U92: 하도급 계약 내역서에 안전관리비 항목을 세분화 한다는 것은 실행편성시에도 하도급 안전관리비 항목을 내역화 한다 부분과하도급법에 대한 상세한 논의가 필요합니다. | X92: 24년3분기(240920) | Z92: Case2. (인정O,채택X)피드백 완료
A93: 83 | B93: CO/D-A/F-CS-2 | C93: 건축 | D93: 본사 | E93: 1000208 | F93: 차장 | G93: 그린솔루션TFT | H93: 제은수 | I93: 45474 | J93: 안희진, 송원일, 김태용 | K93: 안희진 | L93: 수행-공사성 | M93: 건축_마감 | N93: 하자보수 | O93: 도장, 타일공사 직영팀 운영 | P93: • 도장, 타일공사 직영팀 운영 - 고객서비스팀 산하 직영팀 운영(초기 1팀씩, 효과 확인 후 증원) - 평상시 준공현장 하자처리 수행, 필요시 현장 지원 - 현장 지원 금액 현장 원가 안분 및 해당 시공 수량 하도급 감액 | Q93: X | S93: 16 | U93: 작업의 연속성, 우수노동자 고용 유지 등의 장점보다 리스크가 큰 아이디어로 판단됩니다. | Z93: Case1. (인정X)피드백 완료
A94: 84 | B94: CO/Z-PI-CE-3 | C94: 건축 | D94: 본사 | E94: 1000208 | F94: 차장 | G94: 그린솔루션TFT | H94: 제은수 | I94: 45474 | J94: 차원재, 박재보, 고한울 | K94: 박재보 | L94: 공통 | M94: 프로세스 개선 | N94: 공사비 | O94: 준공 이후 하도급 계좌 변경 | P94: • 준공 이후 하도급 계좌 변경으로 노무비 닷컴 해지 | Q94: O | R94: X | S94: 18 | T94: 48 | U94: (건축지원팀 협의 완료) 현장마다 상이한 부분이 있으나 현재, 대부분의 현장준공 후 노무비닷컴에서 미적용현장으로 하여 더 이상 수수료를 지급하지 않고 있습니다. 아이디어는 인정되나 과제화는 필요하지 않는 것으로 협의하였습니다. | X94: 24년3분기(240920) | Z94: Case2. (인정O,채택X)피드백 완료
A95: 85 | B95: CO/I-E-CE-1 | C95: 건축 | D95: 본사 | E95: 1000208 | F95: 차장 | G95: 그린솔루션TFT | H95: 제은수 | I95: 45474 | J95: 양창모, 오정화, | K95: 오정화 | L95: 수행-비공사성 | M95: 전기 | N95: 공사비 | O95: 현장 내 LTE 신호 증폭기 사용 | P95: 현장 내 LTE 신호 증폭기 사용 - SK, KT, LG 협의 현장 내 LTE 중계기 설치 요청 - 현장 진행에 따른 LTE 신호 도달 불가 구간 신호 증폭기 구매/설치 | Q95: O | R95: X | S95: 21 | T95: 63 | U95: 건축전기팀에서 검토 진행중 아이템 | X95: 24년3분기(240920) | Z95: Case2. (인정O,채택X)피드백 완료
A96: 86 | B96: CO/Z-PI-CE-4 | C96: 건축 | D96: 본사 | E96: 1000208 | F96: 차장 | G96: 그린솔루션TFT | H96: 제은수 | I96: 45474 | J96: 차원재, 박재보, 고한울 | K96: 차원재 | L96: 공통 | M96: 프로세스 개선 | N96: 공사비 | O96: 각종 용역, 구독서비스 팀/현장 간 공유 | P96: • 용역, 구독 서비스 관리 게시판 등 신설로 필요시 공유 | Q96: X | S96: 13 | U96: sample 현장기준 구독/용역 서비스 현황에 대한 데이터 필요하며, 공유가 가능한 범위 등 base line 추가 분석 필요, 해당 내용 보강 시 제안서 재검토 가능 | Z96: Case1. (인정X)피드백 완료
A97: 87 | B97: CO/Z-PI-CE-5 | C97: 건축 | D97: 본사 | E97: 1000208 | F97: 차장 | G97: 그린솔루션TFT | H97: 제은수 | I97: 45474 | J97: 차원재, 박재보, 고한울 | K97: 차원재 | L97: 공통 | M97: 프로세스 개선 | N97: 공사비 | O97: 웹하드 서비스 NAS 대체 | P97: • 1개 현장에 NAS 설치 후 전 현장 개별 아이디 공유 사용 • 보안 관련 지속 모니터링 | Q97: X | S97: 14 | U97: 원가효율화팀/DT팀 기 검토 중인 건으로 DT Security 보안사항 검토 시 문제 없으면 NAS대체 진행 예정 | Z97: Case1. (인정X)피드백 완료
A98: 88 | B98: EN/M-M-CE-7 | C98: 건축 | D98: 본사 | E98: 1806183 | F98: 2을 | G98: 그린솔루션TFT | H98: 권민수 | I98: 45474 | J98: 박병규, 박병규, | K98: 박병규 | L98: 설계_기계 | M98: 기계 | N98: 공사비 | O98: 공동주택 냉난방급탕 통합형 열원설비 제안 | P98: • [공동주택 개선방안] - 냉방난방급탕 열원 통합설계 대체 - 공기열 히트펌프 + 수축열 탱크 설계 (전기) | Q98: X | S98: 17 | U98: 시스템 미개발 및 적용시 필요한 법규 개정 필요 | Z98: Case1. (인정X)피드백 완료
A99: 89 | B99: EN/M-M-CE-8 | C99: 건축 | D99: 본사 | E99: 1806183 | F99: 2을 | G99: 그린솔루션TFT | H99: 권민수 | I99: 45474 | J99: 박병규, 박병규, | K99: 박병규 | L99: 설계_기계 | M99: 기계 | N99: 공사비 | O99: 준 개방형 지열설비공사 활용안 | P99: [개선방안] - 개방형 : 공 무너지지 않는 특허를 가진 특정업체 발굴 : 타사 대형현장 방문확인 (w/기계팀) 및 준 개방형 지열 설치 현황 파악 : 무너지지 않는 지열공의 정량적 평가 필요 ex) 100공 설치 中 99공 정상운영 [개선방안] 1. 준 개방형 지열설계로 1) 냉난방 열원 2) 신재생 의무비율 동시 확보 → (당초) 열원설계(냉동기,냉각탑,보일러) → (변경) 지열설비공사 대체로 원가절감 (-8억) 예상 → (당초) 신재생설계(PV,BIPV,집광채광등) → (변경) 지열설비공사 대체로 원가절감 (-2억) 예상 | Q99: O | R99: X | S99: 19 | U99: 준개방형 지열설계업체 검증 및 열원설계 대체보단 비중확대를 통한 원가절감 검토 필요 | X99: 24년3분기(240920) | Z99: Case3. (인정O,채택 검토)피드백 완료
A100: 90 | B100: EN/M-M-CE-9 | C100: 건축 | D100: 본사 | E100: 0600068 | F100: 차장 | G100: 수서역세권TFT | H100: 심은보 | I100: 45474 | J100: 박병규, 박병규, | K100: 박병규 | L100: 설계_기계 | M100: 기계 | N100: 공사비 | O100: 판매시설 주방 및 화장실 직배기 적용으로 시공비 절감 | P100: 당해층에서 배기 할 수 있도록 천정내부 휀 및 주방탈취기 적용 화장실 직배기의 경우 선택적으로 탈취기 적용 중수조 배기덕트도 적용 검토 | Q100: O | R100: O | S100: 24 | T100: 81 | U100: 현장 VE진행 | V100: O | W100: N차(미정) | X100: 24년3분기(240920) | Z100: Case3. (인정O,채택 검토)피드백 완료
...

Sheet (참고)재직자
A1: 사번 | B1: 성명 | C1: 본부 | D1: 소속 | E1: 사업장 | F1: 직급 | G1: 직무 | H1: 구분 | R1: 본부 | S1: 본부 | T1: 소속 | U1: 제안건수
A2: 9207446 | B2: 김우석 | C2: 직속부서 | D2: 대표이사 | E2: 본사 | F2: 사장 | G2: 경영 | H2: 일반직 | R2: 직속부서 | T2: 경영전략실 | U2: =COUNTIFS('1.아이디어LIST'!$G$11:G1037,'(참고)재직자'!T2) -> 0
A3: 9623972 | B3: 박철광 | C3: 인사지원 | D3: 인사기획팀 | E3: 본사 | F3: 임원 | G3: 경영 | H3: 일반직 | T3: 감사팀 | U3: =COUNTIFS('1.아이디어LIST'!$G$11:G1038,'(참고)재직자'!T3) -> 0
A4: 0011256 | B4: 김민석 | C4: 건축 | D4: 건축사업본부장 | E4: 본사 | F4: 임원 | G4: 경영기획 | H4: 일반직 | T4: TOP추진실 | U4: =COUNTIFS('1.아이디어LIST'!$G$11:G1039,'(참고)재직자'!T4) -> 1
A5: 0301116 | B5: 이준명 | C5: 인프라 | D5: 인프라사업본부장 | E5: 본사 | F5: 임원 | G5: 경영 | H5: 일반직 | T5: 계 | U5: =SUM(U2:U4) -> 1
A6: 0010846 | B6: 여성진 | C6: 인사지원 | D6: 인사기획팀 | E6: 본사 | F6: 임원 | G6: 경영 | H6: 일반직 | R6: 기획실 | T6: 기획팀 | U6: =COUNTIFS('1.아이디어LIST'!$G$11:G1041,'(참고)재직자'!T6) -> 2
A7: 9606450 | B7: 이종훈 | C7: 인사지원 | D7: 인사기획팀 | E7: 본사 | F7: 임원 | G7: 사업관리 | H7: 일반직 | T7: 투자전략팀 | U7: =COUNTIFS('1.아이디어LIST'!$G$11:G1042,'(참고)재직자'!T7) -> 3
A8: 0110760 | B8: 김형준 | C8: 인사지원 | D8: 커뮤니케이션담당 | E8: 본사 | F8: 임원 | G8: 홍보 | H8: 일반직 | T8: 기획관리팀 | U8: =COUNTIFS('1.아이디어LIST'!$G$11:G1043,'(참고)재직자'!T8) -> 0
A9: 0702370 | B9: 윤성호 | C9: 개발 | D9: 개발사업본부장 | E9: 본사 | F9: 임원 | G9: 경영 | H9: 일반직 | T9: 내부회계운영팀 | U9: =COUNTIFS('1.아이디어LIST'!$G$11:G1044,'(참고)재직자'!T9) -> 2
A10: 0011259 | B10: 장우성 | C10: 개발 | D10: 전략사업실장 | E10: 본사 | F10: 임원 | G10: 건설영업 | H10: 일반직 | T10: 원가효율화팀 | U10: =COUNTIFS('1.아이디어LIST'!$G$11:G1045,'(참고)재직자'!T10) -> 0
A11: 0110914 | B11: 오용근 | C11: 기획 | D11: 기획실장 | E11: 본사 | F11: 임원 | G11: 경영 | H11: 일반직 | T11: DT팀 | U11: =COUNTIFS('1.아이디어LIST'!$G$11:G1046,'(참고)재직자'!T11) -> 3
A12: 0200581 | B12: 임진규 | C12: 외주구매 | D12: 외주구매실장 | E12: 본사 | F12: 임원 | G12: 경영기획 | H12: 일반직 | T12: 계 | U12: =SUM(U6:U11) -> 10
A13: 0201016 | B13: 정윤상 | C13: 건축 | D13: CS실장 | E13: 본사 | F13: 임원 | G13: 품질 | H13: 일반직 | R13: 법무실 | T13: 법무팀 | U13: =COUNTIFS('1.아이디어LIST'!$G$11:G1048,'(참고)재직자'!T13) -> 0
A14: 0300616 | B14: 박영재 | C14: 해외 | D14: 이라크사업실장 | E14: 해외 | F14: 임원 | G14: 경영 | H14: 일반직 | T14: 계 | U14: =U13 -> 0
A15: 0500077 | B15: 이정수 | C15: 인프라 | D15: 수행혁신실장 | E15: 본사 | F15: 임원 | G15: 사업관리 | H15: 일반직 | R15: 안전환경경영실 | T15: 안전보건기획팀 | U15: =COUNTIFS('1.아이디어LIST'!$G$11:G1050,'(참고)재직자'!T15) -> 0
A16: 0500681 | B16: 황율남 | C16: 개발 | D16: 개발사업실장 | E16: 본사 | F16: 임원 | G16: 건설영업 | H16: 일반직 | T16: 안전보건운영팀 | U16: =COUNTIFS('1.아이디어LIST'!$G$11:G1051,'(참고)재직자'!T16) -> 1
A17: 0500765 | B17: 김주돈 | C17: 인프라 | D17: 토목사업실장 | E17: 본사 | F17: 임원 | G17: 건설영업 | H17: 일반직 | T17: 환경지원팀 | U17: =COUNTIFS('1.아이디어LIST'!$G$11:G1052,'(참고)재직자'!T17) -> 0
A18: 0903441 | B18: 전창수 | C18: 인사지원 | D18: 인사지원실장 | E18: 본사 | F18: 임원 | G18: 경영 | H18: 일반직 | T18: 계 | U18: =SUM(U15:U17) -> 1
A19: 9710188 | B19: 송태을 | C19: 인프라 | D19: 환경사업실장 | E19: 본사 | F19: 임원 | G19: 건설영업 | H19: 일반직 | R19: 경영지원본부 | S19: 인사지원실 | T19: 인사기획팀 | U19: =COUNTIFS('1.아이디어LIST'!$G$11:G1054,'(참고)재직자'!T19) -> 1
A20: 9711103 | B20: 박광호 | C20: 건축 | D20: 건축지원실장 | E20: 본사 | F20: 임원 | G20: 사업관리 | H20: 일반직 | T20: 인사운영팀 | U20: =COUNTIFS('1.아이디어LIST'!$G$11:G1055,'(참고)재직자'!T20) -> 0
A21: 0900062 | B21: 김태형 | C21: 인사지원 | D21: 인사기획팀 | E21: 본사 | F21: 임원 | G21: 법무 | H21: 일반직 | T21: 현장지원팀 | U21: =COUNTIFS('1.아이디어LIST'!$G$11:G1056,'(참고)재직자'!T21) -> 3
A22: 0010487 | B22: 김윤석 | C22: 인프라 | D22: 환경사업PD | E22: 본사 | F22: 임원 | G22: 건설영업 | H22: 일반직 | T22: 홍보팀 | U22: =COUNTIFS('1.아이디어LIST'!$G$11:G1057,'(참고)재직자'!T22) -> 0
A23: 0300506 | B23: 차상민 | C23: 건축 | D23: 경상/제주PD | E23: 본사 | F23: 임원 | G23: 사업관리 | H23: 일반직 | T23: CR지원팀 | U23: =COUNTIFS('1.아이디어LIST'!$G$11:G1058,'(참고)재직자'!T23) -> 0
A24: 0300507 | B24: 송재형 | C24: 건축 | D24: 서울역세권PD | E24: 본사 | F24: 임원 | G24: 사업관리 | H24: 일반직 | S24: 외주구매실 | T24: 외주상생혁신팀 | U24: =COUNTIFS('1.아이디어LIST'!$G$11:G1059,'(참고)재직자'!T24) -> 2
A25: 0500782 | B25: 최은국 | C25: 건축 | D25: 충청/전라PD | E25: 본사 | F25: 임원 | G25: 사업관리 | H25: 일반직 | T25: 외주팀 | U25: =COUNTIFS('1.아이디어LIST'!$G$11:G1060,'(참고)재직자'!T25) -> 11
A26: 9606623 | B26: 김창복 | C26: 건축 | D26: 서울/경기북부PD | E26: 본사 | F26: 임원 | G26: 사업관리 | H26: 일반직 | T26: 구매팀 | U26: =COUNTIFS('1.아이디어LIST'!$G$11:G1061,'(참고)재직자'!T26) -> 7
A27: 9623751 | B27: 황인성 | C27: 인프라 | D27: 토목사업PD | E27: 본사 | F27: 임원 | G27: 시공 | H27: 일반직 | T27: 계 | U27: =SUM(U19:U26) -> 24
A28: 9710346 | B28: 송도화 | C28: 건축 | D28: 경기남부/강원PD | E28: 본사 | F28: 임원 | G28: 사업관리 | H28: 일반직 | R28: 개발사업본부 | T28: 개발기획팀 | U28: =COUNTIFS('1.아이디어LIST'!$G$11:G1063,'(참고)재직자'!T28) -> 0
A29: 0201023 | B29: 김윤해 | C29: 안전환경 | D29: 안전환경경영실장(CSO) | E29: 본사 | F29: 임원 | G29: ESH | H29: 일반직 | T29: 마케팅팀 | U29: =COUNTIFS('1.아이디어LIST'!$G$11:G1064,'(참고)재직자'!T29) -> 0
A30: 0800028 | B30: 강진혁 | C30: 개발 | D30: 마케팅팀 | E30: 본사 | F30: 임원 | G30: 주택마케팅 | H30: 일반직 | T30: 마케팅팀(사업소) | U30: =COUNTIFS('1.아이디어LIST'!$G$11:G1065,'(참고)재직자'!T30) -> 1
A31: 0400915 | B31: 김성수 | C31: 인사지원 | D31: 인사기획팀 | E31: 본사 | F31: 임원 | G31: 사업관리 | H31: 일반직 | T31: 전략사업팀 | U31: =COUNTIFS('1.아이디어LIST'!$G$11:G1066,'(참고)재직자'!T31) -> 0
A32: 9606413 | B32: 이은원 | C32: 인사지원 | D32: 인사기획팀 | E32: 본사 | F32: 임원 | G32: 사업관리 | H32: 일반직 | T32: 개발사업팀 | U32: =COUNTIFS('1.아이디어LIST'!$G$11:G1067,'(참고)재직자'!T32) -> 11
A33: 9624731 | B33: 최원균 | C33: 인사지원 | D33: 인사기획팀 | E33: 본사 | F33: 임원 | G33: 경영 | H33: 일반직 | T33: 개발사업팀(사업소) | U33: =COUNTIFS('1.아이디어LIST'!$G$11:G1068,'(참고)재직자'!T33) -> 1
A34: 9604733 | B34: 최광호 | C34: 인사지원 | D34: 임원실 | E34: 본사 | F34: 고문 | G34: 경영 | H34: 일반직 | T34: 건축영업팀 | U34: =COUNTIFS('1.아이디어LIST'!$G$11:G1069,'(참고)재직자'!T34) -> 10
A35: 0010692 | B35: 한상범 | C35: 건축 | D35: 서울아레나 복합문화시설 | E35: 현장 | F35: 부장 | G35: 시공 | H35: 일반직 | T35: 주택사업팀 | U35: =COUNTIFS('1.아이디어LIST'!$G$11:G1070,'(참고)재직자'!T35) -> 6
A36: 0200563 | B36: 박홍진 | C36: 건축 | D36: 아산배방 생활숙박시설 | E36: 현장 | F36: 부장 | G36: 시공 | H36: 일반직 | T36: 정비사업팀 | U36: =COUNTIFS('1.아이디어LIST'!$G$11:G1071,'(참고)재직자'!T36) -> 3
A37: 0300598 | B37: 이광준 | C37: 건축 | D37: 운암3단지 재건축 | E37: 현장 | F37: 부장 | G37: 시공 | H37: 일반직 | T37: 정비사업팀(사업소) | U37: =COUNTIFS('1.아이디어LIST'!$G$11:G1072,'(참고)재직자'!T37) -> 4
A38: 0300619 | B38: 황광섭 | C38: 건축 | D38: 창원IDC 신축공사 | E38: 현장 | F38: 부장 | G38: 시공 | H38: 일반직 | T38: 마켓솔루션TFT | U38: =COUNTIFS('1.아이디어LIST'!$G$11:G1073,'(참고)재직자'!T38) -> 0
A39: 0301111 | B39: 송원일 | C39: 건축 | D39: 고양 삼송 이지스 데이터센터 | E39: 현장 | F39: 부장 | G39: 시공 | H39: 일반직 | S39: 건축사업부 | T39: 건축지원팀 | U39: =COUNTIFS('1.아이디어LIST'!$G$11:G1074,'(참고)재직자'!T39) -> 22
A40: 0500425 | B40: 김재원 | C40: 건축 | D40: 대전 학하 민간임대 | E40: 현장 | F40: 부장 | G40: 시공 | H40: 일반직 | T40: 기술혁신팀 | U40: =COUNTIFS('1.아이디어LIST'!$G$11:G1075,'(참고)재직자'!T40) -> 44
A41: 0701977 | B41: 이창현 | C41: 건축 | D41: 대전 월평공원 | E41: 현장 | F41: 부장 | G41: 시공 | H41: 일반직 | T41: 건축기계팀 | U41: =COUNTIFS('1.아이디어LIST'!$G$11:G1076,'(참고)재직자'!T41) -> 5
A42: 1104087 | B42: 최영민 | C42: 건축 | D42: 상인천초교주변 재개발 | E42: 현장 | F42: 부장 | G42: 시공 | H42: 일반직 | T42: 건축전기팀 | U42: =COUNTIFS('1.아이디어LIST'!$G$11:G1077,'(참고)재직자'!T42) -> 10
A43: 1300006 | B43: 김태완 | C43: 인프라 | D43: 수도권광역급행철도 C노선(GTX-C | E43: 현장 | F43: 부장 | G43: 시공 | H43: 일반직 | T43: 디자인팀 | U43: =COUNTIFS('1.아이디어LIST'!$G$11:G1077,'(참고)재직자'!T43) -> 26
A44: 0500781 | B44: 최우석 | C44: 건축 | D44: 운영혁신실장 | E44: 본사 | F44: 부장 | G44: 사업관리 | H44: 일반직 | T44: 디자인팀(현장) | U44: =COUNTIFS('1.아이디어LIST'!$G$11:G1078,'(참고)재직자'!T44) -> 1
A45: 0500545 | B45: 김동식 | C45: 외주구매 | D45: 외주팀 | E45: 본사 | F45: 부장 | G45: 외주 | H45: 일반직 | T45: 사업지원팀 | U45: =COUNTIFS('1.아이디어LIST'!$G$11:G1079,'(참고)재직자'!T45) -> 14
A46: 0802059 | B46: 공지강 | C46: 기획 | D46: 기획팀 | E46: 본사 | F46: 부장 | G46: 경영기획 | H46: 일반직 | T46: 건축견적팀 | U46: =COUNTIFS('1.아이디어LIST'!$G$11:G1080,'(참고)재직자'!T46) -> 25
A47: 0802066 | B47: 윤성한 | C47: 인프라 | D47: 인프라지원팀 | E47: 본사 | F47: 부장 | G47: 사업기획 | H47: 일반직 | T47: 품질관리팀 | U47: =COUNTIFS('1.아이디어LIST'!$G$11:G1081,'(참고)재직자'!T47) -> 15
A48: 1300611 | B48: 이상재 | C48: 기획 | D48: 법무팀 | E48: 본사 | F48: 부장 | G48: 법무 | H48: 일반직 | T48: 고객서비스팀 | U48: =COUNTIFS('1.아이디어LIST'!$G$11:G1082,'(참고)재직자'!T48) -> 14
A49: 9606693 | B49: 김상호 | C49: 인프라 | D49: 대전하수처리장 현대화 | E49: 현장 | F49: 부장 | G49: 시공 | H49: 일반직 | T49: 고객서비스팀(현장) | U49: =COUNTIFS('1.아이디어LIST'!$G$11:G1083,'(참고)재직자'!T49) -> 21
A50: 0010683 | B50: 김명수 | C50: 건축 | D50: 진주이현 재건축 | E50: 현장 | F50: 부장 | G50: 시공 | H50: 일반직 | T50: AS지방사업소(창원) | U50: =COUNTIFS('1.아이디어LIST'!$G$11:G1084,'(참고)재직자'!T50) -> 0
A51: 0200580 | B51: 이철우 | C51: 건축 | D51: 부산 당리2구역 재개발 | E51: 현장 | F51: 부장 | G51: 시공 | H51: 일반직 | T51: AS지방사업소(중부) | U51: =COUNTIFS('1.아이디어LIST'!$G$11:G1085,'(참고)재직자'!T51) -> 0
A52: 0201015 | B52: 이용운 | C52: 건축 | D52: 인천 학익4 재개발 | E52: 현장 | F52: 부장 | G52: 시공 | H52: 일반직 | T52: 천안청수(2013)하자 | U52: =COUNTIFS('1.아이디어LIST'!$G$11:G1086,'(참고)재직자'!T52) -> 0
A53: 0201028 | B53: 이상록 | C53: 건축 | D53: 미추8구역 재개발 | E53: 현장 | F53: 부장 | G53: 시공 | H53: 일반직 | T53: S-ONE 프로젝트 하자 | U53: =COUNTIFS('1.아이디어LIST'!$G$11:G1087,'(참고)재직자'!T53) -> 0
A54: 0201224 | B54: 김대환 | C54: 인프라 | D54: 청주국사산업단지 조성공사 | E54: 현장 | F54: 부장 | G54: 시공 | H54: 일반직 | T54: S-ONE 프로젝트(증설) 하자 | U54: =COUNTIFS('1.아이디어LIST'!$G$11:G1088,'(참고)재직자'!T54) -> 0
... A115: 0601366 | B115: 김창욱 | C115: 인프라 | D115: 제2용인테크노밸리 | E115: 현장 | F115: 부장 | G115: 시공 | H115: 일반직 | T115: 부산 당리2구역 재개발 | U115: =COUNTIFS('1.아이디어LIST'!$G$11:G1149,'(참고)재직자'!T115) -> 3
A116: 1002346 | B116: 최규천 | C116: 인프라 | D116: H-테크노밸리 부지조성공사 | E116: 현장 | F116: 부장 | G116: 시공 | H116: 일반직 | P116: xk | T116: 서울아레나 복합문화시설 | U116: =COUNTIFS('1.아이디어LIST'!$G$11:G1150,'(참고)재직자'!T116) -> 25
A117: 9711134 | B117: 최광식 | C117: 인프라 | D117: 양주광적 하수도 2단계 | E117: 현장 | F117: 부장 | G117: 시공 | H117: 일반직 | T117: 원당1구역 재개발 | U117: =COUNTIFS('1.아이디어LIST'!$G$11:G1151,'(참고)재직자'!T117) -> 16
A118: 1001794 | B118: 양진호 | C118: 해외 | D118: 이라크지사 | E118: 해외 | F118: 부장 | G118: 해외영업 | H118: 일반직 | T118: 상인천초교주변 재개발 | U118: =COUNTIFS('1.아이디어LIST'!$G$11:G1152,'(참고)재직자'!T118) -> 5
A119: 0010685 | B119: 문지용 | C119: 건축 | D119: 수서역세권TFT | E119: 본사 | F119: 부장 | G119: 사업관리 | H119: 일반직 | T119: 미추8구역 재개발 | U119: =COUNTIFS('1.아이디어LIST'!$G$11:G1153,'(참고)재직자'!T119) -> 8
A120: 0200218 | B120: 김민석 | C120: 건축 | D120: 잠실MICE TFT | E120: 본사 | F120: 부장 | G120: 사업관리 | H120: 일반직 | T120: 창원IDC 신축공사 | U120: =COUNTIFS('1.아이디어LIST'!$G$11:G1154,'(참고)재직자'!T120) -> 15
A121: 0600095 | B121: 홍승수 | C121: 인사지원 | D121: CR지원팀 | E121: 본사 | F121: 부장 | G121: 홍보 | H121: 일반직 | T121: 영종도 인스파이어 하자 | U121: =COUNTIFS('1.아이디어LIST'!$G$11:G1155,'(참고)재직자'!T121) -> 0
A122: 0701850 | B122: 정창수 | C122: 건축 | D122: 대전역세권 TFT | E122: 본사 | F122: 부장 | G122: 사업관리 | H122: 일반직 | T122: 계 | U122: =SUM(U28:U121) -> 771
A123: 0110659 | B123: 임영진 | C123: 건축 | D123: 디자인팀 | E123: 본사 | F123: 부장 | G123: 디자인설계 | H123: 일반직 | T123: 총계 | U123: =U5+U12+U14+U18+U27+U122 -> 807
A124: 0200314 | B124: 손성일 | C124: 인프라 | D124: 대전하수처리장 현대화 | E124: 현장 | F124: 부장 | G124: PA | H124: 일반직
A125: 0300975 | B125: 이문훈 | C125: 인프라 | D125: 대전하수처리장 현대화 | E125: 현장 | F125: 부장 | G125: ESH | H125: 일반직
A126: 0500072 | B126: 박상준 | C126: 건축 | D126: 아산배방 생활숙박시설 | E126: 현장 | F126: 부장 | G126: 시공 | H126: 일반직
A127: 0500079 | B127: 최성록 | C127: 직속부서 | D127: TOP추진실 | E127: 본사 | F127: 부장 | G127: 경영기획 | H127: 일반직
A128: 0500562 | B128: 최성중 | C128: 건축 | D128: 서울역 역세권 개발사업 CM | E128: 현장 | F128: 부장 | G128: PA | H128: 일반직
A129: 0601376 | B129: 안희진 | C129: 직속부서 | D129: TOP추진실 | E129: 본사 | F129: 부장 | G129: 경영기획 | H129: 일반직
A130: 0701631 | B130: 이형우 | C130: 건축 | D130: 서울역 역세권 개발사업 호텔 | E130: 현장 | F130: 부장 | G130: 시공 | H130: 일반직
A131: 1101071 | B131: 송종원 | C131: 건축 | D131: 서울역 역세권 개발사업 호텔 | E131: 현장 | F131: 부장 | G131: 시공 | H131: 일반직
A132: 1300806 | B132: 김제명 | C132: 건축 | D132: 아산배방 생활숙박시설 | E132: 현장 | F132: 부장 | G132: 공무 | H132: 일반직
A133: 9607032 | B133: 안현철 | C133: 건축 | D133: 아산배방 생활숙박시설 | E133: 현장 | F133: 부장 | G133: PA | H133: 일반직
A134: 9611302 | B134: 진정일 | C134: 건축 | D134: 서울역 역세권 개발사업 CM | E134: 현장 | F134: 부장 | G134: ESH | H134: 일반직
A135: 9623552 | B135: 유현복 | C135: 건축 | D135: 서울역 역세권 개발사업 CM | E135: 현장 | F135: 부장 | G135: 디자인설계 | H135: 일반직
... A172: 1000508 | B172: 박승산 | C172: 건축 | D172: 횡성 병영시설 신축공사 | E172: 현장 | F172: 차장 | G172: 시공 | H172: 일반직
A173: 1104089 | B173: 송지강 | C173: 건축 | D173: 도마변동9 재개발 | E173: 현장 | F173: 차장 | G173: 시공 | H173: 일반직 | I173: 현장
A174: 0285813 | B174: 조형민 | C174: 해외 | D174: 관리재경팀 | E174: 해외 | F174: 차장 | G174: 현장관리 | H174: 일반직 | I174: 현장
A175: 0400577 | B175: 백문수 | C175: 건축 | D175: 건축기계팀 | E175: 본사 | F175: 차장 | G175: 기전 | H175: 일반직 | I175: 현장
A176: 0500185 | B176: 박원근 | C176: 기획 | D176: 기획관리팀 | E176: 본사 | F176: 차장 | G176: 경영기획 | H176: 일반직 | I176: 현장
A177: 0500659 | B177: 노현욱 | C177: 안전환경 | D177: 환경지원팀 | E177: 본사 | F177: 차장 | G177: ESH | H177: 일반직 | I177: 현장
A178: 0700451 | B178: 최중관 | C178: 인프라 | D178: 수주지원팀 | E178: 본사 | F178: 차장 | G178: 건설영업 | H178: 일반직 | I178: 현장
A179: 0700690 | B179: 곽우철 | C179: 인프라 | D179: 인프라신사업팀 | E179: 본사 | F179: 차장 | G179: 사업관리 | H179: 일반직 | I179: 현장
A180: 0700697 | B180: 조형호 | C180: 기획 | D180: RM팀 | E180: 본사 | F180: 차장 | G180: 경영기획 | H180: 일반직 | I180: 현장
A181: 0700706 | B181: 김필중 | C181: 건축 | D181: 건축지원팀 | E181: 본사 | F181: 차장 | G181: 사업관리 | H181: 일반직 | I181: 현장
A182: 0700729 | B182: 장형준 | C182: 해외 | D182: 해외사업팀 | E182: 본사 | F182: 차장 | G182: 해외건설영업 | H182: 일반직 | I182: 현장
A183: 0703032 | B183: 이진학 | C183: 인프라 | D183: 인프라견적팀 | E183: 본사 | F183: 차장 | G183: 견적 | H183: 일반직 | I183: 현장
A184: 0703037 | B184: 박강일 | C184: 건축 | D184: 건축견적팀 | E184: 본사 | F184: 차장 | G184: 견적 | H184: 일반직 | I184: 현장
... A212: 0201253 | B212: 정원태 | C212: 건축 | D212: 건축안전팀 | E212: 본사 | F212: 차장 | G212: ESH | H212: 일반직 | I212: 현장
A213: 0300007 | B213: 이영상 | C213: 인프라 | D213: H-테크노밸리 부지조성공사 | E213: 현장 | F213: 차장 | G213: 공무 | H213: 일반직
A214: 0300210 | B214: 황인성 | C214: 건축 | D214: 서울아레나 복합문화시설 | E214: 현장 | F214: 차장 | G214: ESH | H214: 일반직
A215: 0300215 | B215: 김재형 | C215: 인프라 | D215: 대전하수처리장 현대화 | E215: 현장 | F215: 차장 | G215: ESH | H215: 일반직
A216: 0300222 | B216: 임호택 | C216: 건축 | D216: 수서역 대체주차장 신축공사 | E216: 현장 | F216: 차장 | G216: PA | H216: 일반직
A217: 0300223 | B217: 박규석 | C217: 건축 | D217: 서울역 역세권 개발사업 CM | E217: 현장 | F217: 차장 | G217: ESH | H217: 일반직
A218: 0300313 | B218: 배중호 | C218: 건축 | D218: 부산 당리2구역 재개발 | E218: 현장 | F218: 차장 | G218: 시공 | H218: 일반직
A219: 0300334 | B219: 권순욱 | C219: 인프라 | D219: 도봉산-옥정 광역철도 2공구 | E219: 현장 | F219: 차장 | G219: 시공 | H219: 일반직
A220: 0300537 | B220: 신종식 | C220: 해외 | D220: 공사팀 | E220: 해외 | F220: 차장 | G220: 시공 | H220: 일반직
A221: 0300544 | B221: 조두상 | C221: 건축 | D221: 평택 화양지구 7-2BL 공동주택 | E221: 현장 | F221: 차장 | G221: 시공 | H221: 일반직
A222: 0300770 | B222: 김판근 | C222: 건축 | D222: 창원IDC 신축공사 | E222: 현장 | F222: 차장 | G222: PA | H222: 일반직
A223: 0300881 | B223: 박영규 | C223: 건축 | D223: 서울아레나 복합문화시설 | E223: 현장 | F223: 차장 | G223: 시공 | H223: 일반직
...

Sheet SPC(재직자)_250829 기준
A1: 0400584 | B1: 조동성 | C1: 개발 | D1: ㈜에이치씨앤디 | E1: 현장 | F1: 부장 | G1: 1갑
A2: 2203986 | B2: 정예헌 | C2: 개발 | D2: ㈜에이치씨앤디 | E2: 현장 | F2: 차장 | G2: 1을
A3: 1202926 | B3: 이동건 | C3: 개발 | D3: ㈜에이치씨앤디 | E3: 현장 | F3: 과장 | G3: 2갑
A4: 2203990 | B4: 송영도 | C4: 개발 | D4: ㈜에이치씨앤디 | E4: 현장 | F4: 과장 | G4: 2갑
A5: 1100749 | B5: 박명기 | C5: 개발 | D5: ㈜에이치씨앤디 | E5: 현장 | F5: 과장 | G5: 2갑
A6: 2203989 | B6: 전유림 | C6: 개발 | D6: ㈜에이치씨앤디 | E6: 현장 | F6: 과장 | G6: 2갑
A7: 2203992 | B7: 서정석 | C7: 개발 | D7: ㈜에이치씨앤디 | E7: 현장 | F7: 대리 | G7: 2을
A8: 2203993 | B8: 김윤중 | C8: 개발 | D8: ㈜에이치씨앤디 | E8: 현장 | F8: 대리 | G8: 2을
A9: 2302350 | B9: 김민경 | C9: 개발 | D9: ㈜에이치씨앤디 | E9: 현장 | F9: 사무직4급 | G9: 사무직4급
A10: 9606995 | B10: 임홍구 | C10: 개발 | D10: (주)수서역환승센터복합개발 | E10: 현장 | F10: 부장 | G10: 1갑
A11: 1106425 | B11: 이명휘 | C11: 개발 | D11: (주)수서역환승센터복합개발 | E11: 현장 | F11: 차장 | G11: 1을
A12: 1000556 | B12: 한승연 | C12: 개발 | D12: (주)수서역환승센터복합개발 | E12: 현장 | F12: 차장 | G12: 1을
... A25: 1890016 | B25: 송현주 | C25: 개발 | D25: ㈜서울역북부역세권개발 | E25: 현장 | F25: 사무직(무기) | G25: 사무직(무기)
B31: 유한진 | D31: 전배 (건설 주택사업팀)
B32: 최병규 | D32: 전배 (솔루션 인사이트)
B33: 강영록 | D33: 전배 (건설 전략사업1팀)
B34: 윤성민 | D34: 전배 (솔루션 인사이트)
B35: 정화용 | D35: 전배 (한화인베스트먼트)
B36: 최보윤 | D36: 전배 (솔루션 인사이트)

Sheet Code
A1: 코드 구분
A2: 대분류 | B2: 코드 | C2: 중분류 | D2: 코드 | E2: 소분류 | F2: 코드 | I2: 인정, 채택 구분값
A3: 구조/토목 | B3: EN/S | C3: 건축_골조 | D3: A/S | E3: 공사비 | F3: CE | I3: O | M3: 포상 완료 여부 | N3: 중복 여부 | T3: CFT구성 | U3: 과제 승인 위원회
A4: 설계_건축외부 | B4: EN/EX | C4: 건축_마감 | D4: A/F | E4: 사업비 | F4: BE | I4: X | M4: Case1. (인정X)피드백 완료 | N4: O | T4: O | U4: 1차(240822)
A5: 설계_건축내부 | B5: EN/I | C5: 토목 | D5: C | E5: 하자보수 | F5: CS | I5: 검토중 | M5: Case2. (인정O,채택X)피드백 완료 | T5: O | U5: 2차(240829)
A6: 설계_기계 | B6: EN/M | C6: 전기 | D6: E | E6: 분양 | F6: SA | M6: Case3. (인정O,채택 검토)피드백 완료 | T6: O | U6: 3차(240909)
A7: 설계_전기 | B7: EN/E | C7: 조경 | D7: L | E7: 판관비 | F7: SNA | M7: Case4. (채택)피드백 완료 | T7: O | U7: 4차(241016)
A8: 외주 | B8: PR/C | C8: 기계 | D8: M | E8: 전사경비 | F8: EXP | U8: 5차(241104)
A9: 구매 | B9: PR/P | C9: 기타공종 | D9: Z | P9: EN/S | U9: 6차(241203)
A10: 수행-공사성 | B10: CO/D | C10: 공통가설 | D10: TF | P10: EN/EX | U10: 7차(250114)
A11: 수행-비공사성 | B11: CO/I | C11: 현장관리비 | D11: YY | P11: EN/I | U11: 8차(250219)
A12: 공통 | B12: CO/Z | C12: 보험료 | D12: ID/A | P12: EN/M | U12: 9차(250327)
A13: 인프라 | B13: IN/C | C13: 안전관리비 | D13: ID/H | P13: EN/E | U13: 10차(250423)
A14: 개발/영업 | B14: D/PM | C14: 환경관리비 | D14: ID/P | P14: PR/C | T14: 지급일자 | U14: 11차(250526)
C15: 민원처리비 | D15: ID/R | P15: PR/P | T15: 24년3분기(240920) | U15: 12차(250623)
C16: 기타경비 | D16: ID/Z | P16: CO/D | T16: 24년4분기(241220) | U16: 13차(250825)
C17: 프로세스 개선 | D17: PI | P17: CO/I | T17: 25년1분기(250421) | U17: 14차(250929)
P18: CO/Z | T18: 25년2분기(250721) | U18: 15차(251104)
A19: 1차 담당자 | E19: (참고)공통 담당자 | M19: 건축_골조 | N19: 고한울 | P19: 구조 | Q19: 박준용 | T19: 25년3,4분기(251209) | U19: 16차(251219)
A20: 대분류 | B20: 코드 | C20: 1차 담당자 | E20: 중분류 | F20: 코드 | G20: 공통1 | H20: 공통2 | M20: 건축_마감 | N20: 안희진 | P20: 설계 | Q20: 김태용
A21: 구조/토목 | B21: EN/S | C21: 박준용 | E21: 건축_골조 | F21: A/S | G21: 고한울 | H21: 박준용 | I21: 공사비 | J21: CE | M21: 토목 | N21: 박준용 | P21: 외주 | Q21: 고한울
A22: 설계_건축외부 | B22: EN/EX | C22: 김태용 | E22: 건축_마감 | F22: A/F | G22: 고한울 | H22: 김태용 | I22: 사업비 | J22: BE | M22: 전기 | N22: 오정화 | P22: 구매 | Q22: 박재보 | U22: N차(미정)
A23: 설계_건축내부 | B23: EN/I | C23: 김태용 | E23: 토목 | F23: C | G23: 박준용 | I23: 하자보수 | J23: CS | M23: 조경 | N23: 김태용 | P23: 수행
A24: 설계_기계 | B24: EN/M | C24: 박병규 | E24: 전기 | F24: E | G24: 오정화 | I24: 분양 | J24: SA | M24: 기계 | N24: 박병규 | P24: 공통 | Q24: 박재보
A25: 설계_전기 | B25: EN/E | C25: 오정화 | E25: 조경 | F25: L | G25: 김태용 | I25: 판관비 | J25: SNA | M25: 기타공종 | N25: 박준용
A26: 외주 | B26: PR/C | C26: 고한울 | E26: 기계 | F26: M | G26: 박병규 | I26: 전사경비 | J26: EXP | M26: 공통가설 | N26: 박준용
A27: 구매 | B27: PR/P | C27: 박재보 | E27: 기타공종 | F27: Z | G27: 박준용 | M27: 현장관리비 | N27: 박재보
A28: 수행-공사성 | B28: CO/D | C28: 고한울 | E28: 공통가설 | F28: TF | G28: 박준용 | M28: 보험료 | N28: 박재보
A29: 수행-비공사성 | B29: CO/I | C29: 박재보 | E29: 현장관리비 | F29: YY | G29: 박재보 | M29: 안전관리비 | N29: 박재보
A30: 공통 | B30: CO/Z | C30: 박재보 | E30: 보험료 | F30: ID/A | G30: 박재보 | M30: 환경관리비 | N30: 최재형
A31: 인프라 | B31: IN/C | C31: 김태영 | E31: 안전관리비 | F31: ID/H | G31: 박재보 | M31: 민원처리비 | N31: 박재보
A32: 개발/영업 | B32: D/PM | C32: 박명진 | E32: 환경관리비 | F32: ID/P | G32: 최재형 | M32: 기타경비 | N32: 박재보
C33: 최성록 | E33: 민원처리비 | F33: ID/R | G33: 박재보 | M33: 프로세스 개선 | N33: 박재보
E34: 기타경비 | F34: ID/Z | G34: 박재보
E35: 프로세스 개선 | F35: PI | G35: 박재보
